Workbook

Sheet Leia-me
B1: Indicadores dos municípios de São Paulo: Entregável de amostra
B3: O que é
B4: Uma planilha que junta, para os 645 municípios de SP, oito indicadores de finanças, educação, saúde e economia, de 2015 a 2025, e compara cada município com os de mesmo porte. Tem ainda uma previsão simples da receita, com a incerteza à vista.
B6: O que não é
B7: Não é trabalho feito para um Cliente nem avaliação de nenhuma prefeitura. É uma amostra feita com dado público, para mostrar como a entrega chega às mãos de quem compra. Nenhum número aqui é resultado de Cliente.
B9: Como usar
B10: 1) Vá à aba "Painel". 2) Escolha o município na célula amarela. 3) Leia a tabela, os gráficos e, em "Previsão", a projeção da receita. As abas "Dados", "Referência", "Previsões" e "Municípios" guardam os números de origem; as demais abas são fórmulas sobre elas.
B12: Como conferir um número
B13: Cada fórmula aponta para a aba "Dados" ou "Referência". Cada linha de "Dados" vem do arquivo indicadores_longo.csv, que as consultas SQL do repositório geram. O README do repositório explica, indicador por indicador, o caminho do número bruto até a célula.
B15: Como ler a comparação
B16: A mediana é a dos municípios do mesmo porte (Censo 2022) no mesmo ano. A posição vai de 0% (menor valor da faixa) a 100% (maior). Estar acima ou abaixo não é bom nem ruim por si: depende de escolhas e de contexto do município.
B18: Cuidados
... B25: Tesouro Nacional (Siconfi), IBGE, INEP e DataSUS. Licenças e como cada uma foi verificada: aba "Fontes e licenças".

Sheet Painel
B1: Indicadores dos municípios de São Paulo
B2: Escolha um município na célula amarela. Tudo abaixo e nas abas "Tabela do município" e "Previsão" se recalcula.
B4: Município (escolha na lista) | C4: Ibirá
B5: Código IBGE | C5: =INDEX('Municípios'!$A$2:$A$646,MATCH($C$4,'Municípios'!$B$2:$B$646,0)) -> 3519402
B6: Faixa de porte (municípios parecidos) | C6: =INDEX('Municípios'!$C$2:$C$646,MATCH($C$4,'Municípios'!$B$2:$B$646,0)) -> 3. De 10 a 20 mil
B7: Municípios na faixa | C7: =COUNTIF('Municípios'!$C$2:$C$646,$C$6) -> 120
B8: População (Censo 2022) | C8: =INDEX('Municípios'!$E$2:$E$646,MATCH($C$4,'Municípios'!$B$2:$B$646,0)) -> 11690
B9: Região geográfica imediata (IBGE) | C9: =INDEX('Municípios'!$D$2:$D$646,MATCH($C$4,'Municípios'!$B$2:$B$646,0)) -> São José do Rio Preto
B11: Último valor de cada indicador, comparado com os municípios da faixa
B12: Indicador | C12: Unidade | D12: Último ano com dado | E12: Valor do município | F12: Mediana da faixa | G12: Diferença para a mediana | H12: Posição na faixa (0% a 100%)
B13: Receita corrente por habitante | C13: R$ por habitante, a preços de 2025 | D13: =IFERROR(SUMPRODUCT(MAX(ISNUMBER('Tabela do município'!$C$10:$M$10)*'Tabela do município'!$C$8:$M$8)),"n.d.") -> 2025 | E13: =IFERROR(INDEX('Tabela do município'!$C$10:$M$10,MATCH(D13,'Tabela do município'!$C$8:$M$8,0)),"n.d.") -> 6414.1779 | F13: =IFERROR(INDEX('Referência'!$H$2:$H$554,MATCH($C$6&"|"&D13&"|receita_pc",'Referência'!$A$2:$A$554,0)),"n.d.") -> 6742.3652 | G13: =IF(AND(ISNUMBER(E13),ISNUMBER(F13)),E13/F13-1,"n.d.") -> -0.048675394 | H13: =IFERROR(COUNTIFS('Dados'!$E$2:$E$7096,$C$6,'Dados'!$D$2:$D$7096,D13,'Dados'!$F$2:$F$7096,"<"&E13)/(INDEX('Referência'!$E$2:$E$554,MATCH($C$6&"|"&D13&"|receita_pc",'Referência'!$A$2:$A$554,0))-1),"n.d.") -> 0.3697479
B14: Dependência de transferências | C14: % da receita corrente | D14: =IFERROR(SUMPRODUCT(MAX(ISNUMBER('Tabela do município'!$C$16:$M$16)*'Tabela do município'!$C$8:$M$8)),"n.d.") -> 2025 | E14: =IFERROR(INDEX('Tabela do município'!$C$16:$M$16,MATCH(D14,'Tabela do município'!$C$8:$M$8,0)),"n.d.") -> 81.244751 | F14: =IFERROR(INDEX('Referência'!$H$2:$H$554,MATCH($C$6&"|"&D14&"|dependencia_transf",'Referência'!$A$2:$A$554,0)),"n.d.") -> 82.033032 | G14: =IF(AND(ISNUMBER(E14),ISNUMBER(F14)),E14/F14-1,"n.d.") -> -0.0096093164 | H14: =IFERROR(COUNTIFS('Dados'!$E$2:$E$7096,$C$6,'Dados'!$D$2:$D$7096,D14,'Dados'!$G$2:$G$7096,"<"&E14)/(INDEX('Referência'!$E$2:$E$554,MATCH($C$6&"|"&D14&"|dependencia_transf",'Referência'!$A$2:$A$554,0))-1),"n.d.") -> 0.41176471
B15: Despesa com saúde por habitante | C15: R$ por habitante, a preços de 2025 | D15: =IFERROR(SUMPRODUCT(MAX(ISNUMBER('Tabela do município'!$C$22:$M$22)*'Tabela do município'!$C$8:$M$8)),"n.d.") -> 2025 | E15: =IFERROR(INDEX('Tabela do município'!$C$22:$M$22,MATCH(D15,'Tabela do município'!$C$8:$M$8,0)),"n.d.") -> 2245.8282 | F15: =IFERROR(INDEX('Referência'!$H$2:$H$554,MATCH($C$6&"|"&D15&"|saude_pc",'Referência'!$A$2:$A$554,0)),"n.d.") -> 1892.7691 | G15: =IF(AND(ISNUMBER(E15),ISNUMBER(F15)),E15/F15-1,"n.d.") -> 0.18653051 | H15: =IFERROR(COUNTIFS('Dados'!$E$2:$E$7096,$C$6,'Dados'!$D$2:$D$7096,D15,'Dados'!$H$2:$H$7096,"<"&E15)/(INDEX('Referência'!$E$2:$E$554,MATCH($C$6&"|"&D15&"|saude_pc",'Referência'!$A$2:$A$554,0))-1),"n.d.") -> 0.78991597
B16: Despesa com educação por habitante | C16: R$ por habitante, a preços de 2025 | D16: =IFERROR(SUMPRODUCT(MAX(ISNUMBER('Tabela do município'!$C$28:$M$28)*'Tabela do município'!$C$8:$M$8)),"n.d.") -> 2025 | E16: =IFERROR(INDEX('Tabela do município'!$C$28:$M$28,MATCH(D16,'Tabela do município'!$C$8:$M$8,0)),"n.d.") -> 1914.6131 | F16: =IFERROR(INDEX('Referência'!$H$2:$H$554,MATCH($C$6&"|"&D16&"|educacao_pc",'Referência'!$A$2:$A$554,0)),"n.d.") -> 2060.5831 | G16: =IF(AND(ISNUMBER(E16),ISNUMBER(F16)),E16/F16-1,"n.d.") -> -0.070839202 | H16: =IFERROR(COUNTIFS('Dados'!$E$2:$E$7096,$C$6,'Dados'!$D$2:$D$7096,D16,'Dados'!$I$2:$I$7096,"<"&E16)/(INDEX('Referência'!$E$2:$E$554,MATCH($C$6&"|"&D16&"|educacao_pc",'Referência'!$A$2:$A$554,0))-1),"n.d.") -> 0.38655462
B17: PIB por habitante | C17: R$ por habitante, a preços de 2025 | D17: =IFERROR(SUMPRODUCT(MAX(ISNUMBER('Tabela do município'!$C$34:$M$34)*'Tabela do município'!$C$8:$M$8)),"n.d.") -> 2023 | E17: =IFERROR(INDEX('Tabela do município'!$C$34:$M$34,MATCH(D17,'Tabela do município'!$C$8:$M$8,0)),"n.d.") -> 38802.657 | F17: =IFERROR(INDEX('Referência'!$H$2:$H$554,MATCH($C$6&"|"&D17&"|pib_pc",'Referência'!$A$2:$A$554,0)),"n.d.") -> 42511.916 | G17: =IF(AND(ISNUMBER(E17),ISNUMBER(F17)),E17/F17-1,"n.d.") -> -0.087252229 | H17: =IFERROR(COUNTIFS('Dados'!$E$2:$E$7096,$C$6,'Dados'!$D$2:$D$7096,D17,'Dados'!$J$2:$J$7096,"<"&E17)/(INDEX('Referência'!$E$2:$E$554,MATCH($C$6&"|"&D17&"|pib_pc",'Referência'!$A$2:$A$554,0))-1),"n.d.") -> 0.43697479
B18: Ideb dos anos iniciais, rede municipal | C18: nota de 0 a 10 | D18: =IFERROR(SUMPRODUCT(MAX(ISNUMBER('Tabela do município'!$C$40:$M$40)*'Tabela do município'!$C$8:$M$8)),"n.d.") -> 2023 | E18: =IFERROR(INDEX('Tabela do município'!$C$40:$M$40,MATCH(D18,'Tabela do município'!$C$8:$M$8,0)),"n.d.") -> 7.3 | F18: =IFERROR(INDEX('Referência'!$H$2:$H$554,MATCH($C$6&"|"&D18&"|ideb",'Referência'!$A$2:$A$554,0)),"n.d.") -> 6.3 | G18: =IF(AND(ISNUMBER(E18),ISNUMBER(F18)),E18/F18-1,"n.d.") -> 0.15873016 | H18: =IFERROR(COUNTIFS('Dados'!$E$2:$E$7096,$C$6,'Dados'!$D$2:$D$7096,D18,'Dados'!$K$2:$K$7096,"<"&E18)/(INDEX('Referência'!$E$2:$E$554,MATCH($C$6&"|"&D18&"|ideb",'Referência'!$A$2:$A$554,0))-1),"n.d.") -> 0.92307692
B19: Nascidos de mães com 7 ou mais consultas de pré-natal | C19: % dos nascidos vivos com número de consultas informado | D19: =IFERROR(SUMPRODUCT(MAX(ISNUMBER('Tabela do município'!$C$46:$M$46)*'Tabela do município'!$C$8:$M$8)),"n.d.") -> 2024 | E19: =IFERROR(INDEX('Tabela do município'!$C$46:$M$46,MATCH(D19,'Tabela do município'!$C$8:$M$8,0)),"n.d.") -> 88.571429 | F19: =IFERROR(INDEX('Referência'!$H$2:$H$554,MATCH($C$6&"|"&D19&"|pre_natal_7mais",'Referência'!$A$2:$A$554,0)),"n.d.") -> 87.380573 | G19: =IF(AND(ISNUMBER(E19),ISNUMBER(F19)),E19/F19-1,"n.d.") -> 0.013628376 | H19: =IFERROR(COUNTIFS('Dados'!$E$2:$E$7096,$C$6,'Dados'!$D$2:$D$7096,D19,'Dados'!$L$2:$L$7096,"<"&E19)/(INDEX('Referência'!$E$2:$E$554,MATCH($C$6&"|"&D19&"|pre_natal_7mais",'Referência'!$A$2:$A$554,0))-1),"n.d.") -> 0.57983193
B21: Como ler: a mediana é a do grupo de municípios do mesmo porte (Censo 2022) no mesmo ano. "Posição" diz quantos municípios da faixa têm valor menor: 0% é o menor valor, 100% é o maior. Estar acima ou abaixo da mediana não é, por si, bom nem ruim: a gestão do município pode ter razão para o desvio.

Sheet Tabela do município
A1: Tabela do município
A2: Município (escolhido na aba Painel) | B2: =Painel!$C$4 -> Ibirá
A3: Código IBGE | B3: =Painel!$C$5 -> 3519402
A4: Faixa de porte | B4: =Painel!$C$6 -> 3. De 10 a 20 mil
A5: As linhas "n.d." são anos em que a fonte não publica ou o município não declarou. Nenhum valor foi estimado.
A8: Indicador | B8: Linha | C8: 2015 | D8: 2016 | E8: 2017 | F8: 2018 | G8: 2019 | H8: 2020 | I8: 2021 | J8: 2022 | K8: 2023 | L8: 2024 | M8: 2025
A10: Receita corrente por habitante | B10: Valor do município | C10: =IFERROR(INDEX('Dados'!$F$2:$F$7096,MATCH($B$3&"|"&C$8,'Dados'!$A$2:$A$7096,0)),"n.d.") -> 5045.6732 | D10: =IFERROR(INDEX('Dados'!$F$2:$F$7096,MATCH($B$3&"|"&D$8,'Dados'!$A$2:$A$7096,0)),"n.d.") -> 4939.5866 | E10: =IFERROR(INDEX('Dados'!$F$2:$F$7096,MATCH($B$3&"|"&E$8,'Dados'!$A$2:$A$7096,0)),"n.d.") -> 4423.0264 | F10: =IFERROR(INDEX('Dados'!$F$2:$F$7096,MATCH($B$3&"|"&F$8,'Dados'!$A$2:$A$7096,0)),"n.d.") -> 4407.8775 | G10: =IFERROR(INDEX('Dados'!$F$2:$F$7096,MATCH($B$3&"|"&G$8,'Dados'!$A$2:$A$7096,0)),"n.d.") -> 4529.9706 | H10: =IFERROR(INDEX('Dados'!$F$2:$F$7096,MATCH($B$3&"|"&H$8,'Dados'!$A$2:$A$7096,0)),"n.d.") -> 4764.5181 | I10: =IFERROR(INDEX('Dados'!$F$2:$F$7096,MATCH($B$3&"|"&I$8,'Dados'!$A$2:$A$7096,0)),"n.d.") -> 4859.3721 | J10: =IFERROR(INDEX('Dados'!$F$2:$F$7096,MATCH($B$3&"|"&J$8,'Dados'!$A$2:$A$7096,0)),"n.d.") -> 5671.5544 | ... M10: =IFERROR(INDEX('Dados'!$F$2:$F$7096,MATCH($B$3&"|"&M$8,'Dados'!$A$2:$A$7096,0)),"n.d.") -> 6414.1779
B11: Mediana da faixa | C11: =IFERROR(INDEX('Referência'!$H$2:$H$554,MATCH($B$4&"|"&C$8&"|receita_pc",'Referência'!$A$2:$A$554,0)),"n.d.") -> 4329.0905 | D11: =IFERROR(INDEX('Referência'!$H$2:$H$554,MATCH($B$4&"|"&D$8&"|receita_pc",'Referência'!$A$2:$A$554,0)),"n.d.") -> 4326.2518 | E11: =IFERROR(INDEX('Referência'!$H$2:$H$554,MATCH($B$4&"|"&E$8&"|receita_pc",'Referência'!$A$2:$A$554,0)),"n.d.") -> 4209.9006 | F11: =IFERROR(INDEX('Referência'!$H$2:$H$554,MATCH($B$4&"|"&F$8&"|receita_pc",'Referência'!$A$2:$A$554,0)),"n.d.") -> 4395.399 | G11: =IFERROR(INDEX('Referência'!$H$2:$H$554,MATCH($B$4&"|"&G$8&"|receita_pc",'Referência'!$A$2:$A$554,0)),"n.d.") -> 4530.5635 | H11: =IFERROR(INDEX('Referência'!$H$2:$H$554,MATCH($B$4&"|"&H$8&"|receita_pc",'Referência'!$A$2:$A$554,0)),"n.d.") -> 4707.0642 | I11: =IFERROR(INDEX('Referência'!$H$2:$H$554,MATCH($B$4&"|"&I$8&"|receita_pc",'Referência'!$A$2:$A$554,0)),"n.d.") -> 4997.4084 | J11: =IFERROR(INDEX('Referência'!$H$2:$H$554,MATCH($B$4&"|"&J$8&"|receita_pc",'Referência'!$A$2:$A$554,0)),"n.d.") -> 5956.9405 | ... M11: =IFERROR(INDEX('Referência'!$H$2:$H$554,MATCH($B$4&"|"&M$8&"|receita_pc",'Referência'!$A$2:$A$554,0)),"n.d.") -> 6742.3652
B12: 1º quartil da faixa | C12: =IFERROR(INDEX('Referência'!$G$2:$G$554,MATCH($B$4&"|"&C$8&"|receita_pc",'Referência'!$A$2:$A$554,0)),"n.d.") -> 3837.6036 | D12: =IFERROR(INDEX('Referência'!$G$2:$G$554,MATCH($B$4&"|"&D$8&"|receita_pc",'Referência'!$A$2:$A$554,0)),"n.d.") -> 3841.4824 | E12: =IFERROR(INDEX('Referência'!$G$2:$G$554,MATCH($B$4&"|"&E$8&"|receita_pc",'Referência'!$A$2:$A$554,0)),"n.d.") -> 3791.0285 | F12: =IFERROR(INDEX('Referência'!$G$2:$G$554,MATCH($B$4&"|"&F$8&"|receita_pc",'Referência'!$A$2:$A$554,0)),"n.d.") -> 3915.0146 | G12: =IFERROR(INDEX('Referência'!$G$2:$G$554,MATCH($B$4&"|"&G$8&"|receita_pc",'Referência'!$A$2:$A$554,0)),"n.d.") -> 3990.5777 | H12: =IFERROR(INDEX('Referência'!$G$2:$G$554,MATCH($B$4&"|"&H$8&"|receita_pc",'Referência'!$A$2:$A$554,0)),"n.d.") -> 4168.6221 | I12: =IFERROR(INDEX('Referência'!$G$2:$G$554,MATCH($B$4&"|"&I$8&"|receita_pc",'Referência'!$A$2:$A$554,0)),"n.d.") -> 4460.0029 | J12: =IFERROR(INDEX('Referência'!$G$2:$G$554,MATCH($B$4&"|"&J$8&"|receita_pc",'Referência'!$A$2:$A$554,0)),"n.d.") -> 5347.5222 | ... M12: =IFERROR(INDEX('Referência'!$G$2:$G$554,MATCH($B$4&"|"&M$8&"|receita_pc",'Referência'!$A$2:$A$554,0)),"n.d.") -> 6044.0109
B13: 3º quartil da faixa | C13: =IFERROR(INDEX('Referência'!$I$2:$I$554,MATCH($B$4&"|"&C$8&"|receita_pc",'Referência'!$A$2:$A$554,0)),"n.d.") -> 5046.4745 | D13: =IFERROR(INDEX('Referência'!$I$2:$I$554,MATCH($B$4&"|"&D$8&"|receita_pc",'Referência'!$A$2:$A$554,0)),"n.d.") -> 4966.3621 | E13: =IFERROR(INDEX('Referência'!$I$2:$I$554,MATCH($B$4&"|"&E$8&"|receita_pc",'Referência'!$A$2:$A$554,0)),"n.d.") -> 4769.173 | F13: =IFERROR(INDEX('Referência'!$I$2:$I$554,MATCH($B$4&"|"&F$8&"|receita_pc",'Referência'!$A$2:$A$554,0)),"n.d.") -> 4923.4427 | G13: =IFERROR(INDEX('Referência'!$I$2:$I$554,MATCH($B$4&"|"&G$8&"|receita_pc",'Referência'!$A$2:$A$554,0)),"n.d.") -> 5061.9004 | H13: =IFERROR(INDEX('Referência'!$I$2:$I$554,MATCH($B$4&"|"&H$8&"|receita_pc",'Referência'!$A$2:$A$554,0)),"n.d.") -> 5307.5948 | I13: =IFERROR(INDEX('Referência'!$I$2:$I$554,MATCH($B$4&"|"&I$8&"|receita_pc",'Referência'!$A$2:$A$554,0)),"n.d.") -> 5518.02 | J13: =IFERROR(INDEX('Referência'!$I$2:$I$554,MATCH($B$4&"|"&J$8&"|receita_pc",'Referência'!$A$2:$A$554,0)),"n.d.") -> 6665.3613 | ... M13: =IFERROR(INDEX('Referência'!$I$2:$I$554,MATCH($B$4&"|"&M$8&"|receita_pc",'Referência'!$A$2:$A$554,0)),"n.d.") -> 7498.9354
B14: Diferença do município para a mediana | C14: =IF(AND(ISNUMBER(C10),ISNUMBER(C11)),C10/C11-1,"n.d.") -> 0.16552731 | D14: =IF(AND(ISNUMBER(D10),ISNUMBER(D11)),D10/D11-1,"n.d.") -> 0.14177049 | E14: =IF(AND(ISNUMBER(E10),ISNUMBER(E11)),E10/E11-1,"n.d.") -> 0.050624899 | F14: =IF(AND(ISNUMBER(F10),ISNUMBER(F11)),F10/F11-1,"n.d.") -> 0.002838999 | G14: =IF(AND(ISNUMBER(G10),ISNUMBER(G11)),G10/G11-1,"n.d.") -> -0.0001308539 | H14: =IF(AND(ISNUMBER(H10),ISNUMBER(H11)),H10/H11-1,"n.d.") -> 0.012205877 | I14: =IF(AND(ISNUMBER(I10),ISNUMBER(I11)),I10/I11-1,"n.d.") -> -0.027621584 | J14: =IF(AND(ISNUMBER(J10),ISNUMBER(J11)),J10/J11-1,"n.d.") -> -0.047908159 | ... M14: =IF(AND(ISNUMBER(M10),ISNUMBER(M11)),M10/M11-1,"n.d.") -> -0.048675394
A16: Dependência de transferências | B16: Valor do município | C16: =IFERROR(INDEX('Dados'!$G$2:$G$7096,MATCH($B$3&"|"&C$8,'Dados'!$A$2:$A$7096,0)),"n.d.") -> 79.928505 | D16: =IFERROR(INDEX('Dados'!$G$2:$G$7096,MATCH($B$3&"|"&D$8,'Dados'!$A$2:$A$7096,0)),"n.d.") -> 81.987635 | E16: =IFERROR(INDEX('Dados'!$G$2:$G$7096,MATCH($B$3&"|"&E$8,'Dados'!$A$2:$A$7096,0)),"n.d.") -> 79.996101 | F16: =IFERROR(INDEX('Dados'!$G$2:$G$7096,MATCH($B$3&"|"&F$8,'Dados'!$A$2:$A$7096,0)),"n.d.") -> 79.703073 | G16: =IFERROR(INDEX('Dados'!$G$2:$G$7096,MATCH($B$3&"|"&G$8,'Dados'!$A$2:$A$7096,0)),"n.d.") -> 82.049398 | H16: =IFERROR(INDEX('Dados'!$G$2:$G$7096,MATCH($B$3&"|"&H$8,'Dados'!$A$2:$A$7096,0)),"n.d.") -> 83.909266 | I16: =IFERROR(INDEX('Dados'!$G$2:$G$7096,MATCH($B$3&"|"&I$8,'Dados'!$A$2:$A$7096,0)),"n.d.") -> 83.521184 | J16: =IFERROR(INDEX('Dados'!$G$2:$G$7096,MATCH($B$3&"|"&J$8,'Dados'!$A$2:$A$7096,0)),"n.d.") -> 81.939577 | ... M16: =IFERROR(INDEX('Dados'!$G$2:$G$7096,MATCH($B$3&"|"&M$8,'Dados'!$A$2:$A$7096,0)),"n.d.") -> 81.244751
B17: Mediana da faixa | C17: =IFERROR(INDEX('Referência'!$H$2:$H$554,MATCH($B$4&"|"&C$8&"|dependencia_transf",'Referência'!$A$2:$A$554,0)),"n.d.") -> 84.913758 | D17: =IFERROR(INDEX('Referência'!$H$2:$H$554,MATCH($B$4&"|"&D$8&"|dependencia_transf",'Referência'!$A$2:$A$554,0)),"n.d.") -> 84.853356 | E17: =IFERROR(INDEX('Referência'!$H$2:$H$554,MATCH($B$4&"|"&E$8&"|dependencia_transf",'Referência'!$A$2:$A$554,0)),"n.d.") -> 84.084433 | F17: =IFERROR(INDEX('Referência'!$H$2:$H$554,MATCH($B$4&"|"&F$8&"|dependencia_transf",'Referência'!$A$2:$A$554,0)),"n.d.") -> 84.003347 | G17: =IFERROR(INDEX('Referência'!$H$2:$H$554,MATCH($B$4&"|"&G$8&"|dependencia_transf",'Referência'!$A$2:$A$554,0)),"n.d.") -> 83.739095 | H17: =IFERROR(INDEX('Referência'!$H$2:$H$554,MATCH($B$4&"|"&H$8&"|dependencia_transf",'Referência'!$A$2:$A$554,0)),"n.d.") -> 84.357034 | I17: =IFERROR(INDEX('Referência'!$H$2:$H$554,MATCH($B$4&"|"&I$8&"|dependencia_transf",'Referência'!$A$2:$A$554,0)),"n.d.") -> 83.823769 | J17: =IFERROR(INDEX('Referência'!$H$2:$H$554,MATCH($B$4&"|"&J$8&"|dependencia_transf",'Referência'!$A$2:$A$554,0)),"n.d.") -> 82.536062 | ... M17: =IFERROR(INDEX('Referência'!$H$2:$H$554,MATCH($B$4&"|"&M$8&"|dependencia_transf",'Referência'!$A$2:$A$554,0)),"n.d.") -> 82.033032
B18: 1º quartil da faixa | C18: =IFERROR(INDEX('Referência'!$G$2:$G$554,MATCH($B$4&"|"&C$8&"|dependencia_transf",'Referência'!$A$2:$A$554,0)),"n.d.") -> 79.360838 | D18: =IFERROR(INDEX('Referência'!$G$2:$G$554,MATCH($B$4&"|"&D$8&"|dependencia_transf",'Referência'!$A$2:$A$554,0)),"n.d.") -> 78.747321 | E18: =IFERROR(INDEX('Referência'!$G$2:$G$554,MATCH($B$4&"|"&E$8&"|dependencia_transf",'Referência'!$A$2:$A$554,0)),"n.d.") -> 77.730738 | F18: =IFERROR(INDEX('Referência'!$G$2:$G$554,MATCH($B$4&"|"&F$8&"|dependencia_transf",'Referência'!$A$2:$A$554,0)),"n.d.") -> 78.385379 | G18: =IFERROR(INDEX('Referência'!$G$2:$G$554,MATCH($B$4&"|"&G$8&"|dependencia_transf",'Referência'!$A$2:$A$554,0)),"n.d.") -> 79.089062 | H18: =IFERROR(INDEX('Referência'!$G$2:$G$554,MATCH($B$4&"|"&H$8&"|dependencia_transf",'Referência'!$A$2:$A$554,0)),"n.d.") -> 79.968899 | I18: =IFERROR(INDEX('Referência'!$G$2:$G$554,MATCH($B$4&"|"&I$8&"|dependencia_transf",'Referência'!$A$2:$A$554,0)),"n.d.") -> 80.656487 | J18: =IFERROR(INDEX('Referência'!$G$2:$G$554,MATCH($B$4&"|"&J$8&"|dependencia_transf",'Referência'!$A$2:$A$554,0)),"n.d.") -> 78.622791 | ... M18: =IFERROR(INDEX('Referência'!$G$2:$G$554,MATCH($B$4&"|"&M$8&"|dependencia_transf",'Referência'!$A$2:$A$554,0)),"n.d.") -> 78.914381
B19: 3º quartil da faixa | C19: =IFERROR(INDEX('Referência'!$I$2:$I$554,MATCH($B$4&"|"&C$8&"|dependencia_transf",'Referência'!$A$2:$A$554,0)),"n.d.") -> 87.33432 | D19: =IFERROR(INDEX('Referência'!$I$2:$I$554,MATCH($B$4&"|"&D$8&"|dependencia_transf",'Referência'!$A$2:$A$554,0)),"n.d.") -> 89.401164 | E19: =IFERROR(INDEX('Referência'!$I$2:$I$554,MATCH($B$4&"|"&E$8&"|dependencia_transf",'Referência'!$A$2:$A$554,0)),"n.d.") -> 86.894214 | F19: =IFERROR(INDEX('Referência'!$I$2:$I$554,MATCH($B$4&"|"&F$8&"|dependencia_transf",'Referência'!$A$2:$A$554,0)),"n.d.") -> 87.921012 | G19: =IFERROR(INDEX('Referência'!$I$2:$I$554,MATCH($B$4&"|"&G$8&"|dependencia_transf",'Referência'!$A$2:$A$554,0)),"n.d.") -> 86.664912 | H19: =IFERROR(INDEX('Referência'!$I$2:$I$554,MATCH($B$4&"|"&H$8&"|dependencia_transf",'Referência'!$A$2:$A$554,0)),"n.d.") -> 87.141898 | I19: =IFERROR(INDEX('Referência'!$I$2:$I$554,MATCH($B$4&"|"&I$8&"|dependencia_transf",'Referência'!$A$2:$A$554,0)),"n.d.") -> 87.668969 | J19: =IFERROR(INDEX('Referência'!$I$2:$I$554,MATCH($B$4&"|"&J$8&"|dependencia_transf",'Referência'!$A$2:$A$554,0)),"n.d.") -> 86.027153 | ... M19: =IFERROR(INDEX('Referência'!$I$2:$I$554,MATCH($B$4&"|"&M$8&"|dependencia_transf",'Referência'!$A$2:$A$554,0)),"n.d.") -> 85.825342
B20: Diferença do município para a mediana | C20: =IF(AND(ISNUMBER(C16),ISNUMBER(C17)),C16/C17-1,"n.d.") -> -0.058709598 | D20: =IF(AND(ISNUMBER(D16),ISNUMBER(D17)),D16/D17-1,"n.d.") -> -0.033772635 | E20: =IF(AND(ISNUMBER(E16),ISNUMBER(E17)),E16/E17-1,"n.d.") -> -0.048621752 | F20: =IF(AND(ISNUMBER(F16),ISNUMBER(F17)),F16/F17-1,"n.d.") -> -0.051191706 | G20: =IF(AND(ISNUMBER(G16),ISNUMBER(G17)),G16/G17-1,"n.d.") -> -0.020178121 | H20: =IF(AND(ISNUMBER(H16),ISNUMBER(H17)),H16/H17-1,"n.d.") -> -0.0053080115 | I20: =IF(AND(ISNUMBER(I16),ISNUMBER(I17)),I16/I17-1,"n.d.") -> -0.0036097783 | J20: =IF(AND(ISNUMBER(J16),ISNUMBER(J17)),J16/J17-1,"n.d.") -> -0.0072269669 | ... M20: =IF(AND(ISNUMBER(M16),ISNUMBER(M17)),M16/M17-1,"n.d.") -> -0.0096093164
A22: Despesa com saúde por habitante | B22: Valor do município | C22: =IFERROR(INDEX('Dados'!$H$2:$H$7096,MATCH($B$3&"|"&C$8,'Dados'!$A$2:$A$7096,0)),"n.d.") -> 1057.2097 | D22: =IFERROR(INDEX('Dados'!$H$2:$H$7096,MATCH($B$3&"|"&D$8,'Dados'!$A$2:$A$7096,0)),"n.d.") -> 1138.1876 | E22: =IFERROR(INDEX('Dados'!$H$2:$H$7096,MATCH($B$3&"|"&E$8,'Dados'!$A$2:$A$7096,0)),"n.d.") -> 1063.1911 | F22: =IFERROR(INDEX('Dados'!$H$2:$H$7096,MATCH($B$3&"|"&F$8,'Dados'!$A$2:$A$7096,0)),"n.d.") -> 1196.3399 | G22: =IFERROR(INDEX('Dados'!$H$2:$H$7096,MATCH($B$3&"|"&G$8,'Dados'!$A$2:$A$7096,0)),"n.d.") -> 1169.1047 | H22: =IFERROR(INDEX('Dados'!$H$2:$H$7096,MATCH($B$3&"|"&H$8,'Dados'!$A$2:$A$7096,0)),"n.d.") -> 1390.2012 | I22: =IFERROR(INDEX('Dados'!$H$2:$H$7096,MATCH($B$3&"|"&I$8,'Dados'!$A$2:$A$7096,0)),"n.d.") -> 1410.7054 | J22: =IFERROR(INDEX('Dados'!$H$2:$H$7096,MATCH($B$3&"|"&J$8,'Dados'!$A$2:$A$7096,0)),"n.d.") -> 1502.2682 | ... M22: =IFERROR(INDEX('Dados'!$H$2:$H$7096,MATCH($B$3&"|"&M$8,'Dados'!$A$2:$A$7096,0)),"n.d.") -> 2245.8282
B23: Mediana da faixa | C23: =IFERROR(INDEX('Referência'!$H$2:$H$554,MATCH($B$4&"|"&C$8&"|saude_pc",'Referência'!$A$2:$A$554,0)),"n.d.") -> 1134.7828 | D23: =IFERROR(INDEX('Referência'!$H$2:$H$554,MATCH($B$4&"|"&D$8&"|saude_pc",'Referência'!$A$2:$A$554,0)),"n.d.") -> 1102.9277 | E23: =IFERROR(INDEX('Referência'!$H$2:$H$554,MATCH($B$4&"|"&E$8&"|saude_pc",'Referência'!$A$2:$A$554,0)),"n.d.") -> 1094.0141 | F23: =IFERROR(INDEX('Referência'!$H$2:$H$554,MATCH($B$4&"|"&F$8&"|saude_pc",'Referência'!$A$2:$A$554,0)),"n.d.") -> 1164.7485 | G23: =IFERROR(INDEX('Referência'!$H$2:$H$554,MATCH($B$4&"|"&G$8&"|saude_pc",'Referência'!$A$2:$A$554,0)),"n.d.") -> 1198.6196 | H23: =IFERROR(INDEX('Referência'!$H$2:$H$554,MATCH($B$4&"|"&H$8&"|saude_pc",'Referência'!$A$2:$A$554,0)),"n.d.") -> 1376.0859 | I23: =IFERROR(INDEX('Referência'!$H$2:$H$554,MATCH($B$4&"|"&I$8&"|saude_pc",'Referência'!$A$2:$A$554,0)),"n.d.") -> 1394.7782 | J23: =IFERROR(INDEX('Referência'!$H$2:$H$554,MATCH($B$4&"|"&J$8&"|saude_pc",'Referência'!$A$2:$A$554,0)),"n.d.") -> 1585.4145 | ... M23: =IFERROR(INDEX('Referência'!$H$2:$H$554,MATCH($B$4&"|"&M$8&"|saude_pc",'Referência'!$A$2:$A$554,0)),"n.d.") -> 1892.7691
B24: 1º quartil da faixa | C24: =IFERROR(INDEX('Referência'!$G$2:$G$554,MATCH($B$4&"|"&C$8&"|saude_pc",'Referência'!$A$2:$A$554,0)),"n.d.") -> 992.23257 | D24: =IFERROR(INDEX('Referência'!$G$2:$G$554,MATCH($B$4&"|"&D$8&"|saude_pc",'Referência'!$A$2:$A$554,0)),"n.d.") -> 964.24772 | E24: =IFERROR(INDEX('Referência'!$G$2:$G$554,MATCH($B$4&"|"&E$8&"|saude_pc",'Referência'!$A$2:$A$554,0)),"n.d.") -> 937.86276 | F24: =IFERROR(INDEX('Referência'!$G$2:$G$554,MATCH($B$4&"|"&F$8&"|saude_pc",'Referência'!$A$2:$A$554,0)),"n.d.") -> 1024.3356 | G24: =IFERROR(INDEX('Referência'!$G$2:$G$554,MATCH($B$4&"|"&G$8&"|saude_pc",'Referência'!$A$2:$A$554,0)),"n.d.") -> 1026.5609 | H24: =IFERROR(INDEX('Referência'!$G$2:$G$554,MATCH($B$4&"|"&H$8&"|saude_pc",'Referência'!$A$2:$A$554,0)),"n.d.") -> 1164.7231 | I24: =IFERROR(INDEX('Referência'!$G$2:$G$554,MATCH($B$4&"|"&I$8&"|saude_pc",'Referência'!$A$2:$A$554,0)),"n.d.") -> 1133.1248 | J24: =IFERROR(INDEX('Referência'!$G$2:$G$554,MATCH($B$4&"|"&J$8&"|saude_pc",'Referência'!$A$2:$A$554,0)),"n.d.") -> 1413.5459 | ... M24: =IFERROR(INDEX('Referência'!$G$2:$G$554,MATCH($B$4&"|"&M$8&"|saude_pc",'Referência'!$A$2:$A$554,0)),"n.d.") -> 1625.7944
B25: 3º quartil da faixa | C25: =IFERROR(INDEX('Referência'!$I$2:$I$554,MATCH($B$4&"|"&C$8&"|saude_pc",'Referência'!$A$2:$A$554,0)),"n.d.") -> 1307.5431 | D25: =IFERROR(INDEX('Referência'!$I$2:$I$554,MATCH($B$4&"|"&D$8&"|saude_pc",'Referência'!$A$2:$A$554,0)),"n.d.") -> 1268.6569 | E25: =IFERROR(INDEX('Referência'!$I$2:$I$554,MATCH($B$4&"|"&E$8&"|saude_pc",'Referência'!$A$2:$A$554,0)),"n.d.") -> 1286.3042 | F25: =IFERROR(INDEX('Referência'!$I$2:$I$554,MATCH($B$4&"|"&F$8&"|saude_pc",'Referência'!$A$2:$A$554,0)),"n.d.") -> 1357.7814 | G25: =IFERROR(INDEX('Referência'!$I$2:$I$554,MATCH($B$4&"|"&G$8&"|saude_pc",'Referência'!$A$2:$A$554,0)),"n.d.") -> 1397.4541 | H25: =IFERROR(INDEX('Referência'!$I$2:$I$554,MATCH($B$4&"|"&H$8&"|saude_pc",'Referência'!$A$2:$A$554,0)),"n.d.") -> 1564.8586 | I25: =IFERROR(INDEX('Referência'!$I$2:$I$554,MATCH($B$4&"|"&I$8&"|saude_pc",'Referência'!$A$2:$A$554,0)),"n.d.") -> 1558.8712 | J25: =IFERROR(INDEX('Referência'!$I$2:$I$554,MATCH($B$4&"|"&J$8&"|saude_pc",'Referência'!$A$2:$A$554,0)),"n.d.") -> 1800.2935 | ... M25: =IFERROR(INDEX('Referência'!$I$2:$I$554,MATCH($B$4&"|"&M$8&"|saude_pc",'Referência'!$A$2:$A$554,0)),"n.d.") -> 2175.6439
B26: Diferença do município para a mediana | C26: =IF(AND(ISNUMBER(C22),ISNUMBER(C23)),C22/C23-1,"n.d.") -> -0.068359498 | D26: =IF(AND(ISNUMBER(D22),ISNUMBER(D23)),D22/D23-1,"n.d.") -> 0.031969365 | E26: =IF(AND(ISNUMBER(E22),ISNUMBER(E23)),E22/E23-1,"n.d.") -> -0.028174288 | F26: =IF(AND(ISNUMBER(F22),ISNUMBER(F23)),F22/F23-1,"n.d.") -> 0.027122918 | G26: =IF(AND(ISNUMBER(G22),ISNUMBER(G23)),G22/G23-1,"n.d.") -> -0.024624052 | H26: =IF(AND(ISNUMBER(H22),ISNUMBER(H23)),H22/H23-1,"n.d.") -> 0.010257548 | I26: =IF(AND(ISNUMBER(I22),ISNUMBER(I23)),I22/I23-1,"n.d.") -> 0.011419115 | J26: =IF(AND(ISNUMBER(J22),ISNUMBER(J23)),J22/J23-1,"n.d.") -> -0.052444483 | ... M26: =IF(AND(ISNUMBER(M22),ISNUMBER(M23)),M22/M23-1,"n.d.") -> 0.18653051
A28: Despesa com educação por habitante | B28: Valor do município | C28: =IFERROR(INDEX('Dados'!$I$2:$I$7096,MATCH($B$3&"|"&C$8,'Dados'!$A$2:$A$7096,0)),"n.d.") -> 1675.556 | D28: =IFERROR(INDEX('Dados'!$I$2:$I$7096,MATCH($B$3&"|"&D$8,'Dados'!$A$2:$A$7096,0)),"n.d.") -> 1580.2175 | E28: =IFERROR(INDEX('Dados'!$I$2:$I$7096,MATCH($B$3&"|"&E$8,'Dados'!$A$2:$A$7096,0)),"n.d.") -> 1565.7475 | F28: =IFERROR(INDEX('Dados'!$I$2:$I$7096,MATCH($B$3&"|"&F$8,'Dados'!$A$2:$A$7096,0)),"n.d.") -> 1638.7483 | G28: =IFERROR(INDEX('Dados'!$I$2:$I$7096,MATCH($B$3&"|"&G$8,'Dados'!$A$2:$A$7096,0)),"n.d.") -> 1634.753 | H28: =IFERROR(INDEX('Dados'!$I$2:$I$7096,MATCH($B$3&"|"&H$8,'Dados'!$A$2:$A$7096,0)),"n.d.") -> 1522.3292 | I28: =IFERROR(INDEX('Dados'!$I$2:$I$7096,MATCH($B$3&"|"&I$8,'Dados'!$A$2:$A$7096,0)),"n.d.") -> 1726.5476 | J28: =IFERROR(INDEX('Dados'!$I$2:$I$7096,MATCH($B$3&"|"&J$8,'Dados'!$A$2:$A$7096,0)),"n.d.") -> 1815.3785 | ... M28: =IFERROR(INDEX('Dados'!$I$2:$I$7096,MATCH($B$3&"|"&M$8,'Dados'!$A$2:$A$7096,0)),"n.d.") -> 1914.6131
B29: Mediana da faixa | C29: =IFERROR(INDEX('Referência'!$H$2:$H$554,MATCH($B$4&"|"&C$8&"|educacao_pc",'Referência'!$A$2:$A$554,0)),"n.d.") -> 1433.2332 | D29: =IFERROR(INDEX('Referência'!$H$2:$H$554,MATCH($B$4&"|"&D$8&"|educacao_pc",'Referência'!$A$2:$A$554,0)),"n.d.") -> 1430.9668 | E29: =IFERROR(INDEX('Referência'!$H$2:$H$554,MATCH($B$4&"|"&E$8&"|educacao_pc",'Referência'!$A$2:$A$554,0)),"n.d.") -> 1378.745 | F29: =IFERROR(INDEX('Referência'!$H$2:$H$554,MATCH($B$4&"|"&F$8&"|educacao_pc",'Referência'!$A$2:$A$554,0)),"n.d.") -> 1412.1307 | G29: =IFERROR(INDEX('Referência'!$H$2:$H$554,MATCH($B$4&"|"&G$8&"|educacao_pc",'Referência'!$A$2:$A$554,0)),"n.d.") -> 1482.8127 | H29: =IFERROR(INDEX('Referência'!$H$2:$H$554,MATCH($B$4&"|"&H$8&"|educacao_pc",'Referência'!$A$2:$A$554,0)),"n.d.") -> 1286.1207 | I29: =IFERROR(INDEX('Referência'!$H$2:$H$554,MATCH($B$4&"|"&I$8&"|educacao_pc",'Referência'!$A$2:$A$554,0)),"n.d.") -> 1391.767 | J29: =IFERROR(INDEX('Referência'!$H$2:$H$554,MATCH($B$4&"|"&J$8&"|educacao_pc",'Referência'!$A$2:$A$554,0)),"n.d.") -> 1833.279 | ... M29: =IFERROR(INDEX('Referência'!$H$2:$H$554,MATCH($B$4&"|"&M$8&"|educacao_pc",'Referência'!$A$2:$A$554,0)),"n.d.") -> 2060.5831
B30: 1º quartil da faixa | C30: =IFERROR(INDEX('Referência'!$G$2:$G$554,MATCH($B$4&"|"&C$8&"|educacao_pc",'Referência'!$A$2:$A$554,0)),"n.d.") -> 1264.6777 | D30: =IFERROR(INDEX('Referência'!$G$2:$G$554,MATCH($B$4&"|"&D$8&"|educacao_pc",'Referência'!$A$2:$A$554,0)),"n.d.") -> 1206.0409 | E30: =IFERROR(INDEX('Referência'!$G$2:$G$554,MATCH($B$4&"|"&E$8&"|educacao_pc",'Referência'!$A$2:$A$554,0)),"n.d.") -> 1168.6544 | F30: =IFERROR(INDEX('Referência'!$G$2:$G$554,MATCH($B$4&"|"&F$8&"|educacao_pc",'Referência'!$A$2:$A$554,0)),"n.d.") -> 1261.3077 | G30: =IFERROR(INDEX('Referência'!$G$2:$G$554,MATCH($B$4&"|"&G$8&"|educacao_pc",'Referência'!$A$2:$A$554,0)),"n.d.") -> 1256.3262 | H30: =IFERROR(INDEX('Referência'!$G$2:$G$554,MATCH($B$4&"|"&H$8&"|educacao_pc",'Referência'!$A$2:$A$554,0)),"n.d.") -> 1081.6543 | I30: =IFERROR(INDEX('Referência'!$G$2:$G$554,MATCH($B$4&"|"&I$8&"|educacao_pc",'Referência'!$A$2:$A$554,0)),"n.d.") -> 1202.1968 | J30: =IFERROR(INDEX('Referência'!$G$2:$G$554,MATCH($B$4&"|"&J$8&"|educacao_pc",'Referência'!$A$2:$A$554,0)),"n.d.") -> 1597.3244 | ... M30: =IFERROR(INDEX('Referência'!$G$2:$G$554,MATCH($B$4&"|"&M$8&"|educacao_pc",'Referência'!$A$2:$A$554,0)),"n.d.") -> 1745.3489
B31: 3º quartil da faixa | C31: =IFERROR(INDEX('Referência'!$I$2:$I$554,MATCH($B$4&"|"&C$8&"|educacao_pc",'Referência'!$A$2:$A$554,0)),"n.d.") -> 1749.83 | D31: =IFERROR(INDEX('Referência'!$I$2:$I$554,MATCH($B$4&"|"&D$8&"|educacao_pc",'Referência'!$A$2:$A$554,0)),"n.d.") -> 1663.8167 | E31: =IFERROR(INDEX('Referência'!$I$2:$I$554,MATCH($B$4&"|"&E$8&"|educacao_pc",'Referência'!$A$2:$A$554,0)),"n.d.") -> 1628.7719 | F31: =IFERROR(INDEX('Referência'!$I$2:$I$554,MATCH($B$4&"|"&F$8&"|educacao_pc",'Referência'!$A$2:$A$554,0)),"n.d.") -> 1647.515 | G31: =IFERROR(INDEX('Referência'!$I$2:$I$554,MATCH($B$4&"|"&G$8&"|educacao_pc",'Referência'!$A$2:$A$554,0)),"n.d.") -> 1656.732 | H31: =IFERROR(INDEX('Referência'!$I$2:$I$554,MATCH($B$4&"|"&H$8&"|educacao_pc",'Referência'!$A$2:$A$554,0)),"n.d.") -> 1483.5668 | I31: =IFERROR(INDEX('Referência'!$I$2:$I$554,MATCH($B$4&"|"&I$8&"|educacao_pc",'Referência'!$A$2:$A$554,0)),"n.d.") -> 1635.058 | J31: =IFERROR(INDEX('Referência'!$I$2:$I$554,MATCH($B$4&"|"&J$8&"|educacao_pc",'Referência'!$A$2:$A$554,0)),"n.d.") -> 2135.0595 | ... M31: =IFERROR(INDEX('Referência'!$I$2:$I$554,MATCH($B$4&"|"&M$8&"|educacao_pc",'Referência'!$A$2:$A$554,0)),"n.d.") -> 2344.0346
B32: Diferença do município para a mediana | C32: =IF(AND(ISNUMBER(C28),ISNUMBER(C29)),C28/C29-1,"n.d.") -> 0.16907418 | D32: =IF(AND(ISNUMBER(D28),ISNUMBER(D29)),D28/D29-1,"n.d.") -> 0.10430061 | E32: =IF(AND(ISNUMBER(E28),ISNUMBER(E29)),E28/E29-1,"n.d.") -> 0.13563238 | F32: =IF(AND(ISNUMBER(F28),ISNUMBER(F29)),F28/F29-1,"n.d.") -> 0.16047925 | G32: =IF(AND(ISNUMBER(G28),ISNUMBER(G29)),G28/G29-1,"n.d.") -> 0.10246756 | H32: =IF(AND(ISNUMBER(H28),ISNUMBER(H29)),H28/H29-1,"n.d.") -> 0.18365966 | I32: =IF(AND(ISNUMBER(I28),ISNUMBER(I29)),I28/I29-1,"n.d.") -> 0.24054351 | J32: =IF(AND(ISNUMBER(J28),ISNUMBER(J29)),J28/J29-1,"n.d.") -> -0.009764196 | ... M32: =IF(AND(ISNUMBER(M28),ISNUMBER(M29)),M28/M29-1,"n.d.") -> -0.070839202
A34: PIB por habitante | B34: Valor do município | C34: =IFERROR(INDEX('Dados'!$J$2:$J$7096,MATCH($B$3&"|"&C$8,'Dados'!$A$2:$A$7096,0)),"n.d.") -> 30283.692 | D34: =IFERROR(INDEX('Dados'!$J$2:$J$7096,MATCH($B$3&"|"&D$8,'Dados'!$A$2:$A$7096,0)),"n.d.") -> 29505.838 | E34: =IFERROR(INDEX('Dados'!$J$2:$J$7096,MATCH($B$3&"|"&E$8,'Dados'!$A$2:$A$7096,0)),"n.d.") -> 31068.419 | F34: =IFERROR(INDEX('Dados'!$J$2:$J$7096,MATCH($B$3&"|"&F$8,'Dados'!$A$2:$A$7096,0)),"n.d.") -> 29739.55 | G34: =IFERROR(INDEX('Dados'!$J$2:$J$7096,MATCH($B$3&"|"&G$8,'Dados'!$A$2:$A$7096,0)),"n.d.") -> 27716.105 | H34: =IFERROR(INDEX('Dados'!$J$2:$J$7096,MATCH($B$3&"|"&H$8,'Dados'!$A$2:$A$7096,0)),"n.d.") -> 29068.691 | I34: =IFERROR(INDEX('Dados'!$J$2:$J$7096,MATCH($B$3&"|"&I$8,'Dados'!$A$2:$A$7096,0)),"n.d.") -> 31532.342 | J34: =IFERROR(INDEX('Dados'!$J$2:$J$7096,MATCH($B$3&"|"&J$8,'Dados'!$A$2:$A$7096,0)),"n.d.") -> 33576.387 | ... M34: =IFERROR(INDEX('Dados'!$J$2:$J$7096,MATCH($B$3&"|"&M$8,'Dados'!$A$2:$A$7096,0)),"n.d.") -> n.d.
B35: Mediana da faixa | C35: =IFERROR(INDEX('Referência'!$H$2:$H$554,MATCH($B$4&"|"&C$8&"|pib_pc",'Referência'!$A$2:$A$554,0)),"n.d.") -> 33277.793 | D35: =IFERROR(INDEX('Referência'!$H$2:$H$554,MATCH($B$4&"|"&D$8&"|pib_pc",'Referência'!$A$2:$A$554,0)),"n.d.") -> 33258.864 | E35: =IFERROR(INDEX('Referência'!$H$2:$H$554,MATCH($B$4&"|"&E$8&"|pib_pc",'Referência'!$A$2:$A$554,0)),"n.d.") -> 33251.675 | F35: =IFERROR(INDEX('Referência'!$H$2:$H$554,MATCH($B$4&"|"&F$8&"|pib_pc",'Referência'!$A$2:$A$554,0)),"n.d.") -> 30201.995 | G35: =IFERROR(INDEX('Referência'!$H$2:$H$554,MATCH($B$4&"|"&G$8&"|pib_pc",'Referência'!$A$2:$A$554,0)),"n.d.") -> 32612.189 | H35: =IFERROR(INDEX('Referência'!$H$2:$H$554,MATCH($B$4&"|"&H$8&"|pib_pc",'Referência'!$A$2:$A$554,0)),"n.d.") -> 35960.585 | I35: =IFERROR(INDEX('Referência'!$H$2:$H$554,MATCH($B$4&"|"&I$8&"|pib_pc",'Referência'!$A$2:$A$554,0)),"n.d.") -> 36497.025 | J35: =IFERROR(INDEX('Referência'!$H$2:$H$554,MATCH($B$4&"|"&J$8&"|pib_pc",'Referência'!$A$2:$A$554,0)),"n.d.") -> 37630.58 | ... M35: =IFERROR(INDEX('Referência'!$H$2:$H$554,MATCH($B$4&"|"&M$8&"|pib_pc",'Referência'!$A$2:$A$554,0)),"n.d.") -> n.d.
B36: 1º quartil da faixa | C36: =IFERROR(INDEX('Referência'!$G$2:$G$554,MATCH($B$4&"|"&C$8&"|pib_pc",'Referência'!$A$2:$A$554,0)),"n.d.") -> 25386.09 | D36: =IFERROR(INDEX('Referência'!$G$2:$G$554,MATCH($B$4&"|"&D$8&"|pib_pc",'Referência'!$A$2:$A$554,0)),"n.d.") -> 25668.627 | E36: =IFERROR(INDEX('Referência'!$G$2:$G$554,MATCH($B$4&"|"&E$8&"|pib_pc",'Referência'!$A$2:$A$554,0)),"n.d.") -> 27109.391 | F36: =IFERROR(INDEX('Referência'!$G$2:$G$554,MATCH($B$4&"|"&F$8&"|pib_pc",'Referência'!$A$2:$A$554,0)),"n.d.") -> 26039.806 | G36: =IFERROR(INDEX('Referência'!$G$2:$G$554,MATCH($B$4&"|"&G$8&"|pib_pc",'Referência'!$A$2:$A$554,0)),"n.d.") -> 26082.265 | H36: =IFERROR(INDEX('Referência'!$G$2:$G$554,MATCH($B$4&"|"&H$8&"|pib_pc",'Referência'!$A$2:$A$554,0)),"n.d.") -> 26607.673 | I36: =IFERROR(INDEX('Referência'!$G$2:$G$554,MATCH($B$4&"|"&I$8&"|pib_pc",'Referência'!$A$2:$A$554,0)),"n.d.") -> 26372.371 | J36: =IFERROR(INDEX('Referência'!$G$2:$G$554,MATCH($B$4&"|"&J$8&"|pib_pc",'Referência'!$A$2:$A$554,0)),"n.d.") -> 27165.744 | ... M36: =IFERROR(INDEX('Referência'!$G$2:$G$554,MATCH($B$4&"|"&M$8&"|pib_pc",'Referência'!$A$2:$A$554,0)),"n.d.") -> n.d.
B37: 3º quartil da faixa | C37: =IFERROR(INDEX('Referência'!$I$2:$I$554,MATCH($B$4&"|"&C$8&"|pib_pc",'Referência'!$A$2:$A$554,0)),"n.d.") -> 47098.282 | D37: =IFERROR(INDEX('Referência'!$I$2:$I$554,MATCH($B$4&"|"&D$8&"|pib_pc",'Referência'!$A$2:$A$554,0)),"n.d.") -> 44950.726 | E37: =IFERROR(INDEX('Referência'!$I$2:$I$554,MATCH($B$4&"|"&E$8&"|pib_pc",'Referência'!$A$2:$A$554,0)),"n.d.") -> 47424.575 | F37: =IFERROR(INDEX('Referência'!$I$2:$I$554,MATCH($B$4&"|"&F$8&"|pib_pc",'Referência'!$A$2:$A$554,0)),"n.d.") -> 42164.019 | G37: =IFERROR(INDEX('Referência'!$I$2:$I$554,MATCH($B$4&"|"&G$8&"|pib_pc",'Referência'!$A$2:$A$554,0)),"n.d.") -> 42832.169 | H37: =IFERROR(INDEX('Referência'!$I$2:$I$554,MATCH($B$4&"|"&H$8&"|pib_pc",'Referência'!$A$2:$A$554,0)),"n.d.") -> 47007.37 | I37: =IFERROR(INDEX('Referência'!$I$2:$I$554,MATCH($B$4&"|"&I$8&"|pib_pc",'Referência'!$A$2:$A$554,0)),"n.d.") -> 48142.299 | J37: =IFERROR(INDEX('Referência'!$I$2:$I$554,MATCH($B$4&"|"&J$8&"|pib_pc",'Referência'!$A$2:$A$554,0)),"n.d.") -> 49051.929 | ... M37: =IFERROR(INDEX('Referência'!$I$2:$I$554,MATCH($B$4&"|"&M$8&"|pib_pc",'Referência'!$A$2:$A$554,0)),"n.d.") -> n.d.
B38: Diferença do município para a mediana | C38: =IF(AND(ISNUMBER(C34),ISNUMBER(C35)),C34/C35-1,"n.d.") -> -0.08997295 | D38: =IF(AND(ISNUMBER(D34),ISNUMBER(D35)),D34/D35-1,"n.d.") -> -0.11284287 | E38: =IF(AND(ISNUMBER(E34),ISNUMBER(E35)),E34/E35-1,"n.d.") -> -0.065658529 | F38: =IF(AND(ISNUMBER(F34),ISNUMBER(F35)),F34/F35-1,"n.d.") -> -0.015311758 | G38: =IF(AND(ISNUMBER(G34),ISNUMBER(G35)),G34/G35-1,"n.d.") -> -0.1501305 | H38: =IF(AND(ISNUMBER(H34),ISNUMBER(H35)),H34/H35-1,"n.d.") -> -0.19165132 | I38: =IF(AND(ISNUMBER(I34),ISNUMBER(I35)),I34/I35-1,"n.d.") -> -0.1360298 | J38: =IF(AND(ISNUMBER(J34),ISNUMBER(J35)),J34/J35-1,"n.d.") -> -0.10773665 | ... M38: =IF(AND(ISNUMBER(M34),ISNUMBER(M35)),M34/M35-1,"n.d.") -> n.d.
A40: Ideb dos anos iniciais, rede municipal | B40: Valor do município | C40: =IFERROR(INDEX('Dados'!$K$2:$K$7096,MATCH($B$3&"|"&C$8,'Dados'!$A$2:$A$7096,0)),"n.d.") -> 7.5 | D40: =IFERROR(INDEX('Dados'!$K$2:$K$7096,MATCH($B$3&"|"&D$8,'Dados'!$A$2:$A$7096,0)),"n.d.") -> n.d. | E40: =IFERROR(INDEX('Dados'!$K$2:$K$7096,MATCH($B$3&"|"&E$8,'Dados'!$A$2:$A$7096,0)),"n.d.") -> 7.5 | F40: =IFERROR(INDEX('Dados'!$K$2:$K$7096,MATCH($B$3&"|"&F$8,'Dados'!$A$2:$A$7096,0)),"n.d.") -> n.d. | G40: =IFERROR(INDEX('Dados'!$K$2:$K$7096,MATCH($B$3&"|"&G$8,'Dados'!$A$2:$A$7096,0)),"n.d.") -> 7.3 | H40: =IFERROR(INDEX('Dados'!$K$2:$K$7096,MATCH($B$3&"|"&H$8,'Dados'!$A$2:$A$7096,0)),"n.d.") -> n.d. | I40: =IFERROR(INDEX('Dados'!$K$2:$K$7096,MATCH($B$3&"|"&I$8,'Dados'!$A$2:$A$7096,0)),"n.d.") -> 6 | J40: =IFERROR(INDEX('Dados'!$K$2:$K$7096,MATCH($B$3&"|"&J$8,'Dados'!$A$2:$A$7096,0)),"n.d.") -> n.d. | ... M40: =IFERROR(INDEX('Dados'!$K$2:$K$7096,MATCH($B$3&"|"&M$8,'Dados'!$A$2:$A$7096,0)),"n.d.") -> n.d.
B41: Mediana da faixa | C41: =IFERROR(INDEX('Referência'!$H$2:$H$554,MATCH($B$4&"|"&C$8&"|ideb",'Referência'!$A$2:$A$554,0)),"n.d.") -> 6.1 | D41: =IFERROR(INDEX('Referência'!$H$2:$H$554,MATCH($B$4&"|"&D$8&"|ideb",'Referência'!$A$2:$A$554,0)),"n.d.") -> n.d. | E41: =IFERROR(INDEX('Referência'!$H$2:$H$554,MATCH($B$4&"|"&E$8&"|ideb",'Referência'!$A$2:$A$554,0)),"n.d.") -> 6.5 | F41: =IFERROR(INDEX('Referência'!$H$2:$H$554,MATCH($B$4&"|"&F$8&"|ideb",'Referência'!$A$2:$A$554,0)),"n.d.") -> n.d. | G41: =IFERROR(INDEX('Referência'!$H$2:$H$554,MATCH($B$4&"|"&G$8&"|ideb",'Referência'!$A$2:$A$554,0)),"n.d.") -> 6.5 | H41: =IFERROR(INDEX('Referência'!$H$2:$H$554,MATCH($B$4&"|"&H$8&"|ideb",'Referência'!$A$2:$A$554,0)),"n.d.") -> n.d. | I41: =IFERROR(INDEX('Referência'!$H$2:$H$554,MATCH($B$4&"|"&I$8&"|ideb",'Referência'!$A$2:$A$554,0)),"n.d.") -> 6.1 | J41: =IFERROR(INDEX('Referência'!$H$2:$H$554,MATCH($B$4&"|"&J$8&"|ideb",'Referência'!$A$2:$A$554,0)),"n.d.") -> n.d. | ... M41: =IFERROR(INDEX('Referência'!$H$2:$H$554,MATCH($B$4&"|"&M$8&"|ideb",'Referência'!$A$2:$A$554,0)),"n.d.") -> n.d.
B42: 1º quartil da faixa | C42: =IFERROR(INDEX('Referência'!$G$2:$G$554,MATCH($B$4&"|"&C$8&"|ideb",'Referência'!$A$2:$A$554,0)),"n.d.") -> 5.9 | D42: =IFERROR(INDEX('Referência'!$G$2:$G$554,MATCH($B$4&"|"&D$8&"|ideb",'Referência'!$A$2:$A$554,0)),"n.d.") -> n.d. | E42: =IFERROR(INDEX('Referência'!$G$2:$G$554,MATCH($B$4&"|"&E$8&"|ideb",'Referência'!$A$2:$A$554,0)),"n.d.") -> 6.2 | F42: =IFERROR(INDEX('Referência'!$G$2:$G$554,MATCH($B$4&"|"&F$8&"|ideb",'Referência'!$A$2:$A$554,0)),"n.d.") -> n.d. | G42: =IFERROR(INDEX('Referência'!$G$2:$G$554,MATCH($B$4&"|"&G$8&"|ideb",'Referência'!$A$2:$A$554,0)),"n.d.") -> 6.3 | H42: =IFERROR(INDEX('Referência'!$G$2:$G$554,MATCH($B$4&"|"&H$8&"|ideb",'Referência'!$A$2:$A$554,0)),"n.d.") -> n.d. | I42: =IFERROR(INDEX('Referência'!$G$2:$G$554,MATCH($B$4&"|"&I$8&"|ideb",'Referência'!$A$2:$A$554,0)),"n.d.") -> 5.8 | J42: =IFERROR(INDEX('Referência'!$G$2:$G$554,MATCH($B$4&"|"&J$8&"|ideb",'Referência'!$A$2:$A$554,0)),"n.d.") -> n.d. | ... M42: =IFERROR(INDEX('Referência'!$G$2:$G$554,MATCH($B$4&"|"&M$8&"|ideb",'Referência'!$A$2:$A$554,0)),"n.d.") -> n.d.
B43: 3º quartil da faixa | C43: =IFERROR(INDEX('Referência'!$I$2:$I$554,MATCH($B$4&"|"&C$8&"|ideb",'Referência'!$A$2:$A$554,0)),"n.d.") -> 6.4 | D43: =IFERROR(INDEX('Referência'!$I$2:$I$554,MATCH($B$4&"|"&D$8&"|ideb",'Referência'!$A$2:$A$554,0)),"n.d.") -> n.d. | E43: =IFERROR(INDEX('Referência'!$I$2:$I$554,MATCH($B$4&"|"&E$8&"|ideb",'Referência'!$A$2:$A$554,0)),"n.d.") -> 6.7 | F43: =IFERROR(INDEX('Referência'!$I$2:$I$554,MATCH($B$4&"|"&F$8&"|ideb",'Referência'!$A$2:$A$554,0)),"n.d.") -> n.d. | G43: =IFERROR(INDEX('Referência'!$I$2:$I$554,MATCH($B$4&"|"&G$8&"|ideb",'Referência'!$A$2:$A$554,0)),"n.d.") -> 6.9 | H43: =IFERROR(INDEX('Referência'!$I$2:$I$554,MATCH($B$4&"|"&H$8&"|ideb",'Referência'!$A$2:$A$554,0)),"n.d.") -> n.d. | I43: =IFERROR(INDEX('Referência'!$I$2:$I$554,MATCH($B$4&"|"&I$8&"|ideb",'Referência'!$A$2:$A$554,0)),"n.d.") -> 6.3 | J43: =IFERROR(INDEX('Referência'!$I$2:$I$554,MATCH($B$4&"|"&J$8&"|ideb",'Referência'!$A$2:$A$554,0)),"n.d.") -> n.d. | ... M43: =IFERROR(INDEX('Referência'!$I$2:$I$554,MATCH($B$4&"|"&M$8&"|ideb",'Referência'!$A$2:$A$554,0)),"n.d.") -> n.d.
B44: Diferença do município para a mediana | C44: =IF(AND(ISNUMBER(C40),ISNUMBER(C41)),C40/C41-1,"n.d.") -> 0.2295082 | D44: =IF(AND(ISNUMBER(D40),ISNUMBER(D41)),D40/D41-1,"n.d.") -> n.d. | E44: =IF(AND(ISNUMBER(E40),ISNUMBER(E41)),E40/E41-1,"n.d.") -> 0.15384615 | F44: =IF(AND(ISNUMBER(F40),ISNUMBER(F41)),F40/F41-1,"n.d.") -> n.d. | G44: =IF(AND(ISNUMBER(G40),ISNUMBER(G41)),G40/G41-1,"n.d.") -> 0.12307692 | H44: =IF(AND(ISNUMBER(H40),ISNUMBER(H41)),H40/H41-1,"n.d.") -> n.d. | I44: =IF(AND(ISNUMBER(I40),ISNUMBER(I41)),I40/I41-1,"n.d.") -> -0.016393443 | J44: =IF(AND(ISNUMBER(J40),ISNUMBER(J41)),J40/J41-1,"n.d.") -> n.d. | ... M44: =IF(AND(ISNUMBER(M40),ISNUMBER(M41)),M40/M41-1,"n.d.") -> n.d.
A46: Nascidos de mães com 7 ou mais consultas de pré-natal | B46: Valor do município | C46: =IFERROR(INDEX('Dados'!$L$2:$L$7096,MATCH($B$3&"|"&C$8,'Dados'!$A$2:$A$7096,0)),"n.d.") -> 90.151515 | D46: =IFERROR(INDEX('Dados'!$L$2:$L$7096,MATCH($B$3&"|"&D$8,'Dados'!$A$2:$A$7096,0)),"n.d.") -> 89.041096 | E46: =IFERROR(INDEX('Dados'!$L$2:$L$7096,MATCH($B$3&"|"&E$8,'Dados'!$A$2:$A$7096,0)),"n.d.") -> 92.465753 | F46: =IFERROR(INDEX('Dados'!$L$2:$L$7096,MATCH($B$3&"|"&F$8,'Dados'!$A$2:$A$7096,0)),"n.d.") -> 82.8125 | G46: =IFERROR(INDEX('Dados'!$L$2:$L$7096,MATCH($B$3&"|"&G$8,'Dados'!$A$2:$A$7096,0)),"n.d.") -> 80.141844 | H46: =IFERROR(INDEX('Dados'!$L$2:$L$7096,MATCH($B$3&"|"&H$8,'Dados'!$A$2:$A$7096,0)),"n.d.") -> 77.862595 | I46: =IFERROR(INDEX('Dados'!$L$2:$L$7096,MATCH($B$3&"|"&I$8,'Dados'!$A$2:$A$7096,0)),"n.d.") -> 82.644628 | J46: =IFERROR(INDEX('Dados'!$L$2:$L$7096,MATCH($B$3&"|"&J$8,'Dados'!$A$2:$A$7096,0)),"n.d.") -> 88.461538 | ... M46: =IFERROR(INDEX('Dados'!$L$2:$L$7096,MATCH($B$3&"|"&M$8,'Dados'!$A$2:$A$7096,0)),"n.d.") -> n.d.
B47: Mediana da faixa | C47: =IFERROR(INDEX('Referência'!$H$2:$H$554,MATCH($B$4&"|"&C$8&"|pre_natal_7mais",'Referência'!$A$2:$A$554,0)),"n.d.") -> 81.857367 | D47: =IFERROR(INDEX('Referência'!$H$2:$H$554,MATCH($B$4&"|"&D$8&"|pre_natal_7mais",'Referência'!$A$2:$A$554,0)),"n.d.") -> 81.31467 | E47: =IFERROR(INDEX('Referência'!$H$2:$H$554,MATCH($B$4&"|"&E$8&"|pre_natal_7mais",'Referência'!$A$2:$A$554,0)),"n.d.") -> 81.713836 | F47: =IFERROR(INDEX('Referência'!$H$2:$H$554,MATCH($B$4&"|"&F$8&"|pre_natal_7mais",'Referência'!$A$2:$A$554,0)),"n.d.") -> 85.278638 | G47: =IFERROR(INDEX('Referência'!$H$2:$H$554,MATCH($B$4&"|"&G$8&"|pre_natal_7mais",'Referência'!$A$2:$A$554,0)),"n.d.") -> 85.251156 | H47: =IFERROR(INDEX('Referência'!$H$2:$H$554,MATCH($B$4&"|"&H$8&"|pre_natal_7mais",'Referência'!$A$2:$A$554,0)),"n.d.") -> 84.094213 | I47: =IFERROR(INDEX('Referência'!$H$2:$H$554,MATCH($B$4&"|"&I$8&"|pre_natal_7mais",'Referência'!$A$2:$A$554,0)),"n.d.") -> 84.638981 | J47: =IFERROR(INDEX('Referência'!$H$2:$H$554,MATCH($B$4&"|"&J$8&"|pre_natal_7mais",'Referência'!$A$2:$A$554,0)),"n.d.") -> 85.893278 | ... M47: =IFERROR(INDEX('Referência'!$H$2:$H$554,MATCH($B$4&"|"&M$8&"|pre_natal_7mais",'Referência'!$A$2:$A$554,0)),"n.d.") -> n.d.
B48: 1º quartil da faixa | C48: =IFERROR(INDEX('Referência'!$G$2:$G$554,MATCH($B$4&"|"&C$8&"|pre_natal_7mais",'Referência'!$A$2:$A$554,0)),"n.d.") -> 76.287388 | D48: =IFERROR(INDEX('Referência'!$G$2:$G$554,MATCH($B$4&"|"&D$8&"|pre_natal_7mais",'Referência'!$A$2:$A$554,0)),"n.d.") -> 76.564456 | E48: =IFERROR(INDEX('Referência'!$G$2:$G$554,MATCH($B$4&"|"&E$8&"|pre_natal_7mais",'Referência'!$A$2:$A$554,0)),"n.d.") -> 77.13575 | F48: =IFERROR(INDEX('Referência'!$G$2:$G$554,MATCH($B$4&"|"&F$8&"|pre_natal_7mais",'Referência'!$A$2:$A$554,0)),"n.d.") -> 78.657407 | G48: =IFERROR(INDEX('Referência'!$G$2:$G$554,MATCH($B$4&"|"&G$8&"|pre_natal_7mais",'Referência'!$A$2:$A$554,0)),"n.d.") -> 80.191711 | H48: =IFERROR(INDEX('Referência'!$G$2:$G$554,MATCH($B$4&"|"&H$8&"|pre_natal_7mais",'Referência'!$A$2:$A$554,0)),"n.d.") -> 78.94697 | I48: =IFERROR(INDEX('Referência'!$G$2:$G$554,MATCH($B$4&"|"&I$8&"|pre_natal_7mais",'Referência'!$A$2:$A$554,0)),"n.d.") -> 79.65317 | J48: =IFERROR(INDEX('Referência'!$G$2:$G$554,MATCH($B$4&"|"&J$8&"|pre_natal_7mais",'Referência'!$A$2:$A$554,0)),"n.d.") -> 80.771755 | ... M48: =IFERROR(INDEX('Referência'!$G$2:$G$554,MATCH($B$4&"|"&M$8&"|pre_natal_7mais",'Referência'!$A$2:$A$554,0)),"n.d.") -> n.d.
B49: 3º quartil da faixa | C49: =IFERROR(INDEX('Referência'!$I$2:$I$554,MATCH($B$4&"|"&C$8&"|pre_natal_7mais",'Referência'!$A$2:$A$554,0)),"n.d.") -> 86.956976 | D49: =IFERROR(INDEX('Referência'!$I$2:$I$554,MATCH($B$4&"|"&D$8&"|pre_natal_7mais",'Referência'!$A$2:$A$554,0)),"n.d.") -> 86.946175 | E49: =IFERROR(INDEX('Referência'!$I$2:$I$554,MATCH($B$4&"|"&E$8&"|pre_natal_7mais",'Referência'!$A$2:$A$554,0)),"n.d.") -> 87.55508 | F49: =IFERROR(INDEX('Referência'!$I$2:$I$554,MATCH($B$4&"|"&F$8&"|pre_natal_7mais",'Referência'!$A$2:$A$554,0)),"n.d.") -> 88.699158 | G49: =IFERROR(INDEX('Referência'!$I$2:$I$554,MATCH($B$4&"|"&G$8&"|pre_natal_7mais",'Referência'!$A$2:$A$554,0)),"n.d.") -> 89.147119 | H49: =IFERROR(INDEX('Referência'!$I$2:$I$554,MATCH($B$4&"|"&H$8&"|pre_natal_7mais",'Referência'!$A$2:$A$554,0)),"n.d.") -> 89.596037 | I49: =IFERROR(INDEX('Referência'!$I$2:$I$554,MATCH($B$4&"|"&I$8&"|pre_natal_7mais",'Referência'!$A$2:$A$554,0)),"n.d.") -> 88.975648 | J49: =IFERROR(INDEX('Referência'!$I$2:$I$554,MATCH($B$4&"|"&J$8&"|pre_natal_7mais",'Referência'!$A$2:$A$554,0)),"n.d.") -> 89.271549 | ... M49: =IFERROR(INDEX('Referência'!$I$2:$I$554,MATCH($B$4&"|"&M$8&"|pre_natal_7mais",'Referência'!$A$2:$A$554,0)),"n.d.") -> n.d.
B50: Diferença do município para a mediana | C50: =IF(AND(ISNUMBER(C46),ISNUMBER(C47)),C46/C47-1,"n.d.") -> 0.1013244 | D50: =IF(AND(ISNUMBER(D46),ISNUMBER(D47)),D46/D47-1,"n.d.") -> 0.09501884 | E50: =IF(AND(ISNUMBER(E46),ISNUMBER(E47)),E46/E47-1,"n.d.") -> 0.13158013 | F50: =IF(AND(ISNUMBER(F46),ISNUMBER(F47)),F46/F47-1,"n.d.") -> -0.028918588 | G50: =IF(AND(ISNUMBER(G46),ISNUMBER(G47)),G46/G47-1,"n.d.") -> -0.059932466 | H50: =IF(AND(ISNUMBER(H46),ISNUMBER(H47)),H46/H47-1,"n.d.") -> -0.074102816 | I50: =IF(AND(ISNUMBER(I46),ISNUMBER(I47)),I46/I47-1,"n.d.") -> -0.02356305 | J50: =IF(AND(ISNUMBER(J46),ISNUMBER(J47)),J46/J47-1,"n.d.") -> 0.029900595 | ... M50: =IF(AND(ISNUMBER(M46),ISNUMBER(M47)),M46/M47-1,"n.d.") -> n.d.
A59: Apoio aos gráficos do Painel (não editar)
A60: Os "#N/D" abaixo são propositais: é assim que o Excel deixa uma linha de gráfico interrompida onde não há dado.
A63: Receita corrente por habitante | B63: Município escolhido | C63: =IF(ISNUMBER(C10),C10,NA()) -> 5045.6732 | D63: =IF(ISNUMBER(D10),D10,NA()) -> 4939.5866 | E63: =IF(ISNUMBER(E10),E10,NA()) -> 4423.0264 | F63: =IF(ISNUMBER(F10),F10,NA()) -> 4407.8775 | G63: =IF(ISNUMBER(G10),G10,NA()) -> 4529.9706 | H63: =IF(ISNUMBER(H10),H10,NA()) -> 4764.5181 | I63: =IF(ISNUMBER(I10),I10,NA()) -> 4859.3721 | J63: =IF(ISNUMBER(J10),J10,NA()) -> 5671.5544 | ... M63: =IF(ISNUMBER(M10),M10,NA()) -> 6414.1779
B64: Mediana da faixa | C64: =IF(ISNUMBER(C11),C11,NA()) -> 4329.0905 | D64: =IF(ISNUMBER(D11),D11,NA()) -> 4326.2518 | E64: =IF(ISNUMBER(E11),E11,NA()) -> 4209.9006 | F64: =IF(ISNUMBER(F11),F11,NA()) -> 4395.399 | G64: =IF(ISNUMBER(G11),G11,NA()) -> 4530.5635 | H64: =IF(ISNUMBER(H11),H11,NA()) -> 4707.0642 | I64: =IF(ISNUMBER(I11),I11,NA()) -> 4997.4084 | J64: =IF(ISNUMBER(J11),J11,NA()) -> 5956.9405 | ... M64: =IF(ISNUMBER(M11),M11,NA()) -> 6742.3652
B65: 1º quartil da faixa | C65: =IF(ISNUMBER(C12),C12,NA()) -> 3837.6036 | D65: =IF(ISNUMBER(D12),D12,NA()) -> 3841.4824 | E65: =IF(ISNUMBER(E12),E12,NA()) -> 3791.0285 | F65: =IF(ISNUMBER(F12),F12,NA()) -> 3915.0146 | G65: =IF(ISNUMBER(G12),G12,NA()) -> 3990.5777 | H65: =IF(ISNUMBER(H12),H12,NA()) -> 4168.6221 | I65: =IF(ISNUMBER(I12),I12,NA()) -> 4460.0029 | J65: =IF(ISNUMBER(J12),J12,NA()) -> 5347.5222 | ... M65: =IF(ISNUMBER(M12),M12,NA()) -> 6044.0109
B66: 3º quartil da faixa | C66: =IF(ISNUMBER(C13),C13,NA()) -> 5046.4745 | D66: =IF(ISNUMBER(D13),D13,NA()) -> 4966.3621 | E66: =IF(ISNUMBER(E13),E13,NA()) -> 4769.173 | F66: =IF(ISNUMBER(F13),F13,NA()) -> 4923.4427 | G66: =IF(ISNUMBER(G13),G13,NA()) -> 5061.9004 | H66: =IF(ISNUMBER(H13),H13,NA()) -> 5307.5948 | I66: =IF(ISNUMBER(I13),I13,NA()) -> 5518.02 | J66: =IF(ISNUMBER(J13),J13,NA()) -> 6665.3613 | ... M66: =IF(ISNUMBER(M13),M13,NA()) -> 7498.9354
A67: Dependência de transferências | B67: Município escolhido | C67: =IF(ISNUMBER(C16),C16,NA()) -> 79.928505 | D67: =IF(ISNUMBER(D16),D16,NA()) -> 81.987635 | E67: =IF(ISNUMBER(E16),E16,NA()) -> 79.996101 | F67: =IF(ISNUMBER(F16),F16,NA()) -> 79.703073 | G67: =IF(ISNUMBER(G16),G16,NA()) -> 82.049398 | H67: =IF(ISNUMBER(H16),H16,NA()) -> 83.909266 | I67: =IF(ISNUMBER(I16),I16,NA()) -> 83.521184 | J67: =IF(ISNUMBER(J16),J16,NA()) -> 81.939577 | ... M67: =IF(ISNUMBER(M16),M16,NA()) -> 81.244751
B68: Mediana da faixa | C68: =IF(ISNUMBER(C17),C17,NA()) -> 84.913758 | D68: =IF(ISNUMBER(D17),D17,NA()) -> 84.853356 | E68: =IF(ISNUMBER(E17),E17,NA()) -> 84.084433 | F68: =IF(ISNUMBER(F17),F17,NA()) -> 84.003347 | G68: =IF(ISNUMBER(G17),G17,NA()) -> 83.739095 | H68: =IF(ISNUMBER(H17),H17,NA()) -> 84.357034 | I68: =IF(ISNUMBER(I17),I17,NA()) -> 83.823769 | J68: =IF(ISNUMBER(J17),J17,NA()) -> 82.536062 | ... M68: =IF(ISNUMBER(M17),M17,NA()) -> 82.033032
B69: 1º quartil da faixa | C69: =IF(ISNUMBER(C18),C18,NA()) -> 79.360838 | D69: =IF(ISNUMBER(D18),D18,NA()) -> 78.747321 | E69: =IF(ISNUMBER(E18),E18,NA()) -> 77.730738 | F69: =IF(ISNUMBER(F18),F18,NA()) -> 78.385379 | G69: =IF(ISNUMBER(G18),G18,NA()) -> 79.089062 | H69: =IF(ISNUMBER(H18),H18,NA()) -> 79.968899 | I69: =IF(ISNUMBER(I18),I18,NA()) -> 80.656487 | J69: =IF(ISNUMBER(J18),J18,NA()) -> 78.622791 | ... M69: =IF(ISNUMBER(M18),M18,NA()) -> 78.914381
B70: 3º quartil da faixa | C70: =IF(ISNUMBER(C19),C19,NA()) -> 87.33432 | D70: =IF(ISNUMBER(D19),D19,NA()) -> 89.401164 | E70: =IF(ISNUMBER(E19),E19,NA()) -> 86.894214 | F70: =IF(ISNUMBER(F19),F19,NA()) -> 87.921012 | G70: =IF(ISNUMBER(G19),G19,NA()) -> 86.664912 | H70: =IF(ISNUMBER(H19),H19,NA()) -> 87.141898 | I70: =IF(ISNUMBER(I19),I19,NA()) -> 87.668969 | J70: =IF(ISNUMBER(J19),J19,NA()) -> 86.027153 | ... M70: =IF(ISNUMBER(M19),M19,NA()) -> 85.825342
A71: Despesa com saúde por habitante | B71: Município escolhido | C71: =IF(ISNUMBER(C22),C22,NA()) -> 1057.2097 | D71: =IF(ISNUMBER(D22),D22,NA()) -> 1138.1876 | E71: =IF(ISNUMBER(E22),E22,NA()) -> 1063.1911 | F71: =IF(ISNUMBER(F22),F22,NA()) -> 1196.3399 | G71: =IF(ISNUMBER(G22),G22,NA()) -> 1169.1047 | H71: =IF(ISNUMBER(H22),H22,NA()) -> 1390.2012 | I71: =IF(ISNUMBER(I22),I22,NA()) -> 1410.7054 | J71: =IF(ISNUMBER(J22),J22,NA()) -> 1502.2682 | ... M71: =IF(ISNUMBER(M22),M22,NA()) -> 2245.8282
B72: Mediana da faixa | C72: =IF(ISNUMBER(C23),C23,NA()) -> 1134.7828 | D72: =IF(ISNUMBER(D23),D23,NA()) -> 1102.9277 | E72: =IF(ISNUMBER(E23),E23,NA()) -> 1094.0141 | F72: =IF(ISNUMBER(F23),F23,NA()) -> 1164.7485 | G72: =IF(ISNUMBER(G23),G23,NA()) -> 1198.6196 | H72: =IF(ISNUMBER(H23),H23,NA()) -> 1376.0859 | I72: =IF(ISNUMBER(I23),I23,NA()) -> 1394.7782 | J72: =IF(ISNUMBER(J23),J23,NA()) -> 1585.4145 | ... M72: =IF(ISNUMBER(M23),M23,NA()) -> 1892.7691
B73: 1º quartil da faixa | C73: =IF(ISNUMBER(C24),C24,NA()) -> 992.23257 | D73: =IF(ISNUMBER(D24),D24,NA()) -> 964.24772 | E73: =IF(ISNUMBER(E24),E24,NA()) -> 937.86276 | F73: =IF(ISNUMBER(F24),F24,NA()) -> 1024.3356 | G73: =IF(ISNUMBER(G24),G24,NA()) -> 1026.5609 | H73: =IF(ISNUMBER(H24),H24,NA()) -> 1164.7231 | I73: =IF(ISNUMBER(I24),I24,NA()) -> 1133.1248 | J73: =IF(ISNUMBER(J24),J24,NA()) -> 1413.5459 | ... M73: =IF(ISNUMBER(M24),M24,NA()) -> 1625.7944
B74: 3º quartil da faixa | C74: =IF(ISNUMBER(C25),C25,NA()) -> 1307.5431 | D74: =IF(ISNUMBER(D25),D25,NA()) -> 1268.6569 | E74: =IF(ISNUMBER(E25),E25,NA()) -> 1286.3042 | F74: =IF(ISNUMBER(F25),F25,NA()) -> 1357.7814 | G74: =IF(ISNUMBER(G25),G25,NA()) -> 1397.4541 | H74: =IF(ISNUMBER(H25),H25,NA()) -> 1564.8586 | I74: =IF(ISNUMBER(I25),I25,NA()) -> 1558.8712 | J74: =IF(ISNUMBER(J25),J25,NA()) -> 1800.2935 | ... M74: =IF(ISNUMBER(M25),M25,NA()) -> 2175.6439
A75: Despesa com educação por habitante | B75: Município escolhido | C75: =IF(ISNUMBER(C28),C28,NA()) -> 1675.556 | D75: =IF(ISNUMBER(D28),D28,NA()) -> 1580.2175 | E75: =IF(ISNUMBER(E28),E28,NA()) -> 1565.7475 | F75: =IF(ISNUMBER(F28),F28,NA()) -> 1638.7483 | G75: =IF(ISNUMBER(G28),G28,NA()) -> 1634.753 | H75: =IF(ISNUMBER(H28),H28,NA()) -> 1522.3292 | I75: =IF(ISNUMBER(I28),I28,NA()) -> 1726.5476 | J75: =IF(ISNUMBER(J28),J28,NA()) -> 1815.3785 | ... M75: =IF(ISNUMBER(M28),M28,NA()) -> 1914.6131
B76: Mediana da faixa | C76: =IF(ISNUMBER(C29),C29,NA()) -> 1433.2332 | D76: =IF(ISNUMBER(D29),D29,NA()) -> 1430.9668 | E76: =IF(ISNUMBER(E29),E29,NA()) -> 1378.745 | F76: =IF(ISNUMBER(F29),F29,NA()) -> 1412.1307 | G76: =IF(ISNUMBER(G29),G29,NA()) -> 1482.8127 | H76: =IF(ISNUMBER(H29),H29,NA()) -> 1286.1207 | I76: =IF(ISNUMBER(I29),I29,NA()) -> 1391.767 | J76: =IF(ISNUMBER(J29),J29,NA()) -> 1833.279 | ... M76: =IF(ISNUMBER(M29),M29,NA()) -> 2060.5831
B77: 1º quartil da faixa | C77: =IF(ISNUMBER(C30),C30,NA()) -> 1264.6777 | D77: =IF(ISNUMBER(D30),D30,NA()) -> 1206.0409 | E77: =IF(ISNUMBER(E30),E30,NA()) -> 1168.6544 | F77: =IF(ISNUMBER(F30),F30,NA()) -> 1261.3077 | G77: =IF(ISNUMBER(G30),G30,NA()) -> 1256.3262 | H77: =IF(ISNUMBER(H30),H30,NA()) -> 1081.6543 | I77: =IF(ISNUMBER(I30),I30,NA()) -> 1202.1968 | J77: =IF(ISNUMBER(J30),J30,NA()) -> 1597.3244 | ... M77: =IF(ISNUMBER(M30),M30,NA()) -> 1745.3489
B78: 3º quartil da faixa | C78: =IF(ISNUMBER(C31),C31,NA()) -> 1749.83 | D78: =IF(ISNUMBER(D31),D31,NA()) -> 1663.8167 | E78: =IF(ISNUMBER(E31),E31,NA()) -> 1628.7719 | F78: =IF(ISNUMBER(F31),F31,NA()) -> 1647.515 | G78: =IF(ISNUMBER(G31),G31,NA()) -> 1656.732 | H78: =IF(ISNUMBER(H31),H31,NA()) -> 1483.5668 | I78: =IF(ISNUMBER(I31),I31,NA()) -> 1635.058 | J78: =IF(ISNUMBER(J31),J31,NA()) -> 2135.0595 | ... M78: =IF(ISNUMBER(M31),M31,NA()) -> 2344.0346
A79: PIB por habitante | B79: Município escolhido | C79: =IF(ISNUMBER(C34),C34,NA()) -> 30283.692 | D79: =IF(ISNUMBER(D34),D34,NA()) -> 29505.838 | E79: =IF(ISNUMBER(E34),E34,NA()) -> 31068.419 | F79: =IF(ISNUMBER(F34),F34,NA()) -> 29739.55 | G79: =IF(ISNUMBER(G34),G34,NA()) -> 27716.105 | H79: =IF(ISNUMBER(H34),H34,NA()) -> 29068.691 | I79: =IF(ISNUMBER(I34),I34,NA()) -> 31532.342 | J79: =IF(ISNUMBER(J34),J34,NA()) -> 33576.387 | ... M79: =IF(ISNUMBER(M34),M34,NA()) -> #N/A
B80: Mediana da faixa | C80: =IF(ISNUMBER(C35),C35,NA()) -> 33277.793 | D80: =IF(ISNUMBER(D35),D35,NA()) -> 33258.864 | E80: =IF(ISNUMBER(E35),E35,NA()) -> 33251.675 | F80: =IF(ISNUMBER(F35),F35,NA()) -> 30201.995 | G80: =IF(ISNUMBER(G35),G35,NA()) -> 32612.189 | H80: =IF(ISNUMBER(H35),H35,NA()) -> 35960.585 | I80: =IF(ISNUMBER(I35),I35,NA()) -> 36497.025 | J80: =IF(ISNUMBER(J35),J35,NA()) -> 37630.58 | ... M80: =IF(ISNUMBER(M35),M35,NA()) -> #N/A
B81: 1º quartil da faixa | C81: =IF(ISNUMBER(C36),C36,NA()) -> 25386.09 | D81: =IF(ISNUMBER(D36),D36,NA()) -> 25668.627 | E81: =IF(ISNUMBER(E36),E36,NA()) -> 27109.391 | F81: =IF(ISNUMBER(F36),F36,NA()) -> 26039.806 | G81: =IF(ISNUMBER(G36),G36,NA()) -> 26082.265 | H81: =IF(ISNUMBER(H36),H36,NA()) -> 26607.673 | I81: =IF(ISNUMBER(I36),I36,NA()) -> 26372.371 | J81: =IF(ISNUMBER(J36),J36,NA()) -> 27165.744 | ... M81: =IF(ISNUMBER(M36),M36,NA()) -> #N/A
B82: 3º quartil da faixa | C82: =IF(ISNUMBER(C37),C37,NA()) -> 47098.282 | D82: =IF(ISNUMBER(D37),D37,NA()) -> 44950.726 | E82: =IF(ISNUMBER(E37),E37,NA()) -> 47424.575 | F82: =IF(ISNUMBER(F37),F37,NA()) -> 42164.019 | G82: =IF(ISNUMBER(G37),G37,NA()) -> 42832.169 | H82: =IF(ISNUMBER(H37),H37,NA()) -> 47007.37 | I82: =IF(ISNUMBER(I37),I37,NA()) -> 48142.299 | J82: =IF(ISNUMBER(J37),J37,NA()) -> 49051.929 | ... M82: =IF(ISNUMBER(M37),M37,NA()) -> #N/A
A83: Ideb dos anos iniciais, rede municipal | B83: Município escolhido | C83: =IF(ISNUMBER(C40),C40,NA()) -> 7.5 | D83: =IF(ISNUMBER(D40),D40,NA()) -> #N/A | E83: =IF(ISNUMBER(E40),E40,NA()) -> 7.5 | F83: =IF(ISNUMBER(F40),F40,NA()) -> #N/A | G83: =IF(ISNUMBER(G40),G40,NA()) -> 7.3 | H83: =IF(ISNUMBER(H40),H40,NA()) -> #N/A | I83: =IF(ISNUMBER(I40),I40,NA()) -> 6 | J83: =IF(ISNUMBER(J40),J40,NA()) -> #N/A | ... M83: =IF(ISNUMBER(M40),M40,NA()) -> #N/A
B84: Mediana da faixa | C84: =IF(ISNUMBER(C41),C41,NA()) -> 6.1 | D84: =IF(ISNUMBER(D41),D41,NA()) -> #N/A | E84: =IF(ISNUMBER(E41),E41,NA()) -> 6.5 | F84: =IF(ISNUMBER(F41),F41,NA()) -> #N/A | G84: =IF(ISNUMBER(G41),G41,NA()) -> 6.5 | H84: =IF(ISNUMBER(H41),H41,NA()) -> #N/A | I84: =IF(ISNUMBER(I41),I41,NA()) -> 6.1 | J84: =IF(ISNUMBER(J41),J41,NA()) -> #N/A | ... M84: =IF(ISNUMBER(M41),M41,NA()) -> #N/A
B85: 1º quartil da faixa | C85: =IF(ISNUMBER(C42),C42,NA()) -> 5.9 | D85: =IF(ISNUMBER(D42),D42,NA()) -> #N/A | E85: =IF(ISNUMBER(E42),E42,NA()) -> 6.2 | F85: =IF(ISNUMBER(F42),F42,NA()) -> #N/A | G85: =IF(ISNUMBER(G42),G42,NA()) -> 6.3 | H85: =IF(ISNUMBER(H42),H42,NA()) -> #N/A | I85: =IF(ISNUMBER(I42),I42,NA()) -> 5.8 | J85: =IF(ISNUMBER(J42),J42,NA()) -> #N/A | ... M85: =IF(ISNUMBER(M42),M42,NA()) -> #N/A
B86: 3º quartil da faixa | C86: =IF(ISNUMBER(C43),C43,NA()) -> 6.4 | D86: =IF(ISNUMBER(D43),D43,NA()) -> #N/A | E86: =IF(ISNUMBER(E43),E43,NA()) -> 6.7 | F86: =IF(ISNUMBER(F43),F43,NA()) -> #N/A | G86: =IF(ISNUMBER(G43),G43,NA()) -> 6.9 | H86: =IF(ISNUMBER(H43),H43,NA()) -> #N/A | I86: =IF(ISNUMBER(I43),I43,NA()) -> 6.3 | J86: =IF(ISNUMBER(J43),J43,NA()) -> #N/A | ... M86: =IF(ISNUMBER(M43),M43,NA()) -> #N/A
A87: Nascidos de mães com 7 ou mais consultas de pré-natal | B87: Município escolhido | C87: =IF(ISNUMBER(C46),C46,NA()) -> 90.151515 | D87: =IF(ISNUMBER(D46),D46,NA()) -> 89.041096 | E87: =IF(ISNUMBER(E46),E46,NA()) -> 92.465753 | F87: =IF(ISNUMBER(F46),F46,NA()) -> 82.8125 | G87: =IF(ISNUMBER(G46),G46,NA()) -> 80.141844 | H87: =IF(ISNUMBER(H46),H46,NA()) -> 77.862595 | I87: =IF(ISNUMBER(I46),I46,NA()) -> 82.644628 | J87: =IF(ISNUMBER(J46),J46,NA()) -> 88.461538 | ... M87: =IF(ISNUMBER(M46),M46,NA()) -> #N/A
B88: Mediana da faixa | C88: =IF(ISNUMBER(C47),C47,NA()) -> 81.857367 | D88: =IF(ISNUMBER(D47),D47,NA()) -> 81.31467 | E88: =IF(ISNUMBER(E47),E47,NA()) -> 81.713836 | F88: =IF(ISNUMBER(F47),F47,NA()) -> 85.278638 | G88: =IF(ISNUMBER(G47),G47,NA()) -> 85.251156 | H88: =IF(ISNUMBER(H47),H47,NA()) -> 84.094213 | I88: =IF(ISNUMBER(I47),I47,NA()) -> 84.638981 | J88: =IF(ISNUMBER(J47),J47,NA()) -> 85.893278 | ... M88: =IF(ISNUMBER(M47),M47,NA()) -> #N/A
B89: 1º quartil da faixa | C89: =IF(ISNUMBER(C48),C48,NA()) -> 76.287388 | D89: =IF(ISNUMBER(D48),D48,NA()) -> 76.564456 | E89: =IF(ISNUMBER(E48),E48,NA()) -> 77.13575 | F89: =IF(ISNUMBER(F48),F48,NA()) -> 78.657407 | G89: =IF(ISNUMBER(G48),G48,NA()) -> 80.191711 | H89: =IF(ISNUMBER(H48),H48,NA()) -> 78.94697 | I89: =IF(ISNUMBER(I48),I48,NA()) -> 79.65317 | J89: =IF(ISNUMBER(J48),J48,NA()) -> 80.771755 | ... M89: =IF(ISNUMBER(M48),M48,NA()) -> #N/A
B90: 3º quartil da faixa | C90: =IF(ISNUMBER(C49),C49,NA()) -> 86.956976 | D90: =IF(ISNUMBER(D49),D49,NA()) -> 86.946175 | E90: =IF(ISNUMBER(E49),E49,NA()) -> 87.55508 | F90: =IF(ISNUMBER(F49),F49,NA()) -> 88.699158 | G90: =IF(ISNUMBER(G49),G49,NA()) -> 89.147119 | H90: =IF(ISNUMBER(H49),H49,NA()) -> 89.596037 | I90: =IF(ISNUMBER(I49),I49,NA()) -> 88.975648 | J90: =IF(ISNUMBER(J49),J49,NA()) -> 89.271549 | ... M90: =IF(ISNUMBER(M49),M49,NA()) -> #N/A

Sheet Previsão
A1: Previsão da receita corrente do município
A2: Município (escolhido na aba Painel) | C2: =Painel!$C$4 -> Ibirá
A3: Código IBGE | C3: =Painel!$C$5 -> 3519402
A4: Grupo de porte do modelo | C4: =INDEX('Municípios'!$F$2:$F$646,MATCH($C$2,'Municípios'!$B$2:$B$646,0)) -> B. De 10 a 50 mil
I5: Apoio ao gráfico (não editar)
A6: Ano | B6: Observado (R$ milhões de 2025) | C6: Previsto | D6: Inferior 80% | E6: Superior 80% | F6: Inferior 95% | G6: Superior 95% | I6: Ano | J6: Observado | K6: Previsto | L6: Inf. 80% | M6: Sup. 80% | N6: Inf. 95% | O6: Sup. 95%
A7: 2015 | B7: =IFERROR(INDEX('Dados'!$M$2:$M$7096,MATCH($C$3&"|"&A7,'Dados'!$A$2:$A$7096,0)),"n.d.") -> 59.846729 | I7: =A7 -> 2015 | J7: =IF(ISNUMBER(B7),B7,NA()) -> 59.846729 | K7: =IF(ISNUMBER(C7),C7,NA()) -> #N/A | L7: =IF(ISNUMBER(D7),D7,NA()) -> #N/A | M7: =IF(ISNUMBER(E7),E7,NA()) -> #N/A | N7: =IF(ISNUMBER(F7),F7,NA()) -> #N/A | O7: =IF(ISNUMBER(G7),G7,NA()) -> #N/A
A8: 2016 | B8: =IFERROR(INDEX('Dados'!$M$2:$M$7096,MATCH($C$3&"|"&A8,'Dados'!$A$2:$A$7096,0)),"n.d.") -> 59.176247 | I8: =A8 -> 2016 | J8: =IF(ISNUMBER(B8),B8,NA()) -> 59.176247 | K8: =IF(ISNUMBER(C8),C8,NA()) -> #N/A | L8: =IF(ISNUMBER(D8),D8,NA()) -> #N/A | M8: =IF(ISNUMBER(E8),E8,NA()) -> #N/A | N8: =IF(ISNUMBER(F8),F8,NA()) -> #N/A | O8: =IF(ISNUMBER(G8),G8,NA()) -> #N/A
A9: 2017 | B9: =IFERROR(INDEX('Dados'!$M$2:$M$7096,MATCH($C$3&"|"&A9,'Dados'!$A$2:$A$7096,0)),"n.d.") -> 53.500928 | I9: =A9 -> 2017 | J9: =IF(ISNUMBER(B9),B9,NA()) -> 53.500928 | K9: =IF(ISNUMBER(C9),C9,NA()) -> #N/A | L9: =IF(ISNUMBER(D9),D9,NA()) -> #N/A | M9: =IF(ISNUMBER(E9),E9,NA()) -> #N/A | N9: =IF(ISNUMBER(F9),F9,NA()) -> #N/A | O9: =IF(ISNUMBER(G9),G9,NA()) -> #N/A
A10: 2018 | B10: =IFERROR(INDEX('Dados'!$M$2:$M$7096,MATCH($C$3&"|"&A10,'Dados'!$A$2:$A$7096,0)),"n.d.") -> 54.05821 | I10: =A10 -> 2018 | J10: =IF(ISNUMBER(B10),B10,NA()) -> 54.05821 | K10: =IF(ISNUMBER(C10),C10,NA()) -> #N/A | L10: =IF(ISNUMBER(D10),D10,NA()) -> #N/A | M10: =IF(ISNUMBER(E10),E10,NA()) -> #N/A | N10: =IF(ISNUMBER(F10),F10,NA()) -> #N/A | O10: =IF(ISNUMBER(G10),G10,NA()) -> #N/A
A11: 2019 | B11: =IFERROR(INDEX('Dados'!$M$2:$M$7096,MATCH($C$3&"|"&A11,'Dados'!$A$2:$A$7096,0)),"n.d.") -> 56.139926 | I11: =A11 -> 2019 | J11: =IF(ISNUMBER(B11),B11,NA()) -> 56.139926 | K11: =IF(ISNUMBER(C11),C11,NA()) -> #N/A | L11: =IF(ISNUMBER(D11),D11,NA()) -> #N/A | M11: =IF(ISNUMBER(E11),E11,NA()) -> #N/A | N11: =IF(ISNUMBER(F11),F11,NA()) -> #N/A | O11: =IF(ISNUMBER(G11),G11,NA()) -> #N/A
A12: 2020 | B12: =IFERROR(INDEX('Dados'!$M$2:$M$7096,MATCH($C$3&"|"&A12,'Dados'!$A$2:$A$7096,0)),"n.d.") -> 59.642237 | I12: =A12 -> 2020 | J12: =IF(ISNUMBER(B12),B12,NA()) -> 59.642237 | K12: =IF(ISNUMBER(C12),C12,NA()) -> #N/A | L12: =IF(ISNUMBER(D12),D12,NA()) -> #N/A | M12: =IF(ISNUMBER(E12),E12,NA()) -> #N/A | N12: =IF(ISNUMBER(F12),F12,NA()) -> #N/A | O12: =IF(ISNUMBER(G12),G12,NA()) -> #N/A
A13: 2021 | B13: =IFERROR(INDEX('Dados'!$M$2:$M$7096,MATCH($C$3&"|"&A13,'Dados'!$A$2:$A$7096,0)),"n.d.") -> 61.417603 | I13: =A13 -> 2021 | J13: =IF(ISNUMBER(B13),B13,NA()) -> 61.417603 | K13: =IF(ISNUMBER(C13),C13,NA()) -> #N/A | L13: =IF(ISNUMBER(D13),D13,NA()) -> #N/A | M13: =IF(ISNUMBER(E13),E13,NA()) -> #N/A | N13: =IF(ISNUMBER(F13),F13,NA()) -> #N/A | O13: =IF(ISNUMBER(G13),G13,NA()) -> #N/A
A14: 2022 | B14: =IFERROR(INDEX('Dados'!$M$2:$M$7096,MATCH($C$3&"|"&A14,'Dados'!$A$2:$A$7096,0)),"n.d.") -> 66.300472 | I14: =A14 -> 2022 | J14: =IF(ISNUMBER(B14),B14,NA()) -> 66.300472 | K14: =IF(ISNUMBER(C14),C14,NA()) -> #N/A | L14: =IF(ISNUMBER(D14),D14,NA()) -> #N/A | M14: =IF(ISNUMBER(E14),E14,NA()) -> #N/A | N14: =IF(ISNUMBER(F14),F14,NA()) -> #N/A | O14: =IF(ISNUMBER(G14),G14,NA()) -> #N/A
A15: 2023 | B15: =IFERROR(INDEX('Dados'!$M$2:$M$7096,MATCH($C$3&"|"&A15,'Dados'!$A$2:$A$7096,0)),"n.d.") -> 67.017445 | I15: =A15 -> 2023 | J15: =IF(ISNUMBER(B15),B15,NA()) -> 67.017445 | K15: =IF(ISNUMBER(C15),C15,NA()) -> #N/A | L15: =IF(ISNUMBER(D15),D15,NA()) -> #N/A | M15: =IF(ISNUMBER(E15),E15,NA()) -> #N/A | N15: =IF(ISNUMBER(F15),F15,NA()) -> #N/A | O15: =IF(ISNUMBER(G15),G15,NA()) -> #N/A
A16: 2024 | B16: =IFERROR(INDEX('Dados'!$M$2:$M$7096,MATCH($C$3&"|"&A16,'Dados'!$A$2:$A$7096,0)),"n.d.") -> 72.802827 | I16: =A16 -> 2024 | J16: =IF(ISNUMBER(B16),B16,NA()) -> 72.802827 | K16: =IF(ISNUMBER(C16),C16,NA()) -> #N/A | L16: =IF(ISNUMBER(D16),D16,NA()) -> #N/A | M16: =IF(ISNUMBER(E16),E16,NA()) -> #N/A | N16: =IF(ISNUMBER(F16),F16,NA()) -> #N/A | O16: =IF(ISNUMBER(G16),G16,NA()) -> #N/A
A17: 2025 | B17: =IFERROR(INDEX('Dados'!$M$2:$M$7096,MATCH($C$3&"|"&A17,'Dados'!$A$2:$A$7096,0)),"n.d.") -> 76.662255 | C17: =B17 -> 76.662255 | D17: =B17 -> 76.662255 | E17: =B17 -> 76.662255 | F17: =B17 -> 76.662255 | G17: =B17 -> 76.662255 | I17: =A17 -> 2025 | J17: =IF(ISNUMBER(B17),B17,NA()) -> 76.662255 | K17: =IF(ISNUMBER(C17),C17,NA()) -> 76.662255 | L17: =IF(ISNUMBER(D17),D17,NA()) -> 76.662255 | M17: =IF(ISNUMBER(E17),E17,NA()) -> 76.662255 | N17: =IF(ISNUMBER(F17),F17,NA()) -> 76.662255 | O17: =IF(ISNUMBER(G17),G17,NA()) -> 76.662255
A18: 2026 | C18: =IFERROR(INDEX('Previsões'!$E$2:$E$1927,MATCH($C$3&"|"&A18,'Previsões'!$A$2:$A$1927,0)),"n.d.") -> 80.464301 | D18: =IFERROR(INDEX('Previsões'!$F$2:$F$1927,MATCH($C$3&"|"&A18,'Previsões'!$A$2:$A$1927,0)),"n.d.") -> 72.416588 | E18: =IFERROR(INDEX('Previsões'!$G$2:$G$1927,MATCH($C$3&"|"&A18,'Previsões'!$A$2:$A$1927,0)),"n.d.") -> 91.314098 | F18: =IFERROR(INDEX('Previsões'!$H$2:$H$1927,MATCH($C$3&"|"&A18,'Previsões'!$A$2:$A$1927,0)),"n.d.") -> 67.926121 | G18: =IFERROR(INDEX('Previsões'!$I$2:$I$1927,MATCH($C$3&"|"&A18,'Previsões'!$A$2:$A$1927,0)),"n.d.") -> 98.871653 | I18: =A18 -> 2026 | J18: =IF(ISNUMBER(B18),B18,NA()) -> #N/A | K18: =IF(ISNUMBER(C18),C18,NA()) -> 80.464301 | L18: =IF(ISNUMBER(D18),D18,NA()) -> 72.416588 | M18: =IF(ISNUMBER(E18),E18,NA()) -> 91.314098 | N18: =IF(ISNUMBER(F18),F18,NA()) -> 67.926121 | O18: =IF(ISNUMBER(G18),G18,NA()) -> 98.871653
A19: 2027 | C19: =IFERROR(INDEX('Previsões'!$E$2:$E$1927,MATCH($C$3&"|"&A19,'Previsões'!$A$2:$A$1927,0)),"n.d.") -> 84.454909 | D19: =IFERROR(INDEX('Previsões'!$F$2:$F$1927,MATCH($C$3&"|"&A19,'Previsões'!$A$2:$A$1927,0)),"n.d.") -> 73.781226 | E19: =IFERROR(INDEX('Previsões'!$G$2:$G$1927,MATCH($C$3&"|"&A19,'Previsões'!$A$2:$A$1927,0)),"n.d.") -> 101.68025 | F19: =IFERROR(INDEX('Previsões'!$H$2:$H$1927,MATCH($C$3&"|"&A19,'Previsões'!$A$2:$A$1927,0)),"n.d.") -> 68.188566 | G19: =IFERROR(INDEX('Previsões'!$I$2:$I$1927,MATCH($C$3&"|"&A19,'Previsões'!$A$2:$A$1927,0)),"n.d.") -> 113.02179 | I19: =A19 -> 2027 | J19: =IF(ISNUMBER(B19),B19,NA()) -> #N/A | K19: =IF(ISNUMBER(C19),C19,NA()) -> 84.454909 | L19: =IF(ISNUMBER(D19),D19,NA()) -> 73.781226 | M19: =IF(ISNUMBER(E19),E19,NA()) -> 101.68025 | N19: =IF(ISNUMBER(F19),F19,NA()) -> 68.188566 | O19: =IF(ISNUMBER(G19),G19,NA()) -> 113.02179
A20: 2028 | C20: =IFERROR(INDEX('Previsões'!$E$2:$E$1927,MATCH($C$3&"|"&A20,'Previsões'!$A$2:$A$1927,0)),"n.d.") -> 88.643431 | D20: =IFERROR(INDEX('Previsões'!$F$2:$F$1927,MATCH($C$3&"|"&A20,'Previsões'!$A$2:$A$1927,0)),"n.d.") -> 74.914188 | E20: =IFERROR(INDEX('Previsões'!$G$2:$G$1927,MATCH($C$3&"|"&A20,'Previsões'!$A$2:$A$1927,0)),"n.d.") -> 114.62948 | F20: =IFERROR(INDEX('Previsões'!$H$2:$H$1927,MATCH($C$3&"|"&A20,'Previsões'!$A$2:$A$1927,0)),"n.d.") -> 67.569155 | G20: =IFERROR(INDEX('Previsões'!$I$2:$I$1927,MATCH($C$3&"|"&A20,'Previsões'!$A$2:$A$1927,0)),"n.d.") -> 128.24456 | I20: =A20 -> 2028 | J20: =IF(ISNUMBER(B20),B20,NA()) -> #N/A | K20: =IF(ISNUMBER(C20),C20,NA()) -> 88.643431 | L20: =IF(ISNUMBER(D20),D20,NA()) -> 74.914188 | M20: =IF(ISNUMBER(E20),E20,NA()) -> 114.62948 | N20: =IF(ISNUMBER(F20),F20,NA()) -> 67.569155 | O20: =IF(ISNUMBER(G20),G20,NA()) -> 128.24456
A22: Leitura
A23: =IFERROR("Em 2028, a receita corrente de "&$C$2&" fica perto de R$ "&ROUND(C20,0)&" milhões (a preços de 2025). Na faixa de 80% do teste do passado, entre R$ "&ROUND(D20,0)&" e R$ "&ROUND(E20,0)&" milhões; na de 95%, entre R$ "&ROUND(F20,0)&" e R$ "&ROUND(G20,0)&" milhões.","Este município não tem os cinco últimos anos de receita válidos: sem previsão.") -> Em 2028, a receita corrente de Ibirá fica perto de R$ 89 milhões (a preços de 2025). Na faixa de 80% do teste do passado, entre R$ 75 e R$ 115 milhões; na de 95%, entre R$ 68 e R$ 128 milhões.
A45: Como a previsão foi feita
A46: Série: receita corrente líquida de deduções, em R$ milhões de 2025 (IPCA), de 2015 a 2025. Método escolhido: "tendencia3", sobre o logaritmo da série.
A47: Três métodos simples concorreram: repetir o último valor, estender a tendência dos 3 últimos anos e estender uma reta ajustada aos 5 últimos anos. Cada um foi testado prevendo o passado (origens de 2019 a 2022, 1 a 3 anos à frente) em todos os municípios com série completa; ficou o de menor erro.
A48: A faixa de incerteza não é fórmula de livro: vem dos erros que o método de fato cometeu, por horizonte e por grupo de porte. A receita dos municípios se move junta de um ano para o outro (inflação, ICMS, transferências), então os quatro anos de origem do teste são quatro "choques" e não 600 observações independentes. Por isso a faixa foi testada deixando uma origem de fora e alargada (fator 1.25 para a de 80% e 1.15 para a de 95%) até a cobertura do teste chegar ao nível prometido.
A49: Limites: método sem informação de fora da série; não conhece mudança de lei, de convênio ou de gestão. Depois do ajuste, a cobertura ficou perto do nível prometido na média, mas com a origem 2022 de fora a faixa de 80% cobriu bem menos (tabela abaixo): um ano que vem depois de um salto de receita (2022) é mais difícil de prever. A Revisão técnica por estatístico registrado no CONRE ainda não está registrada para esta amostra.
A51: Erro do método, ao prever o passado
A52: Método | B52: Anos à frente | C52: Previsões testadas | D52: Erro médio absoluto (%) | E52: Viés (%) | F52: Escolhido
A53: ingenuo | B53: 1 | C53: 2516 | D53: 7.0078913 | E53: 5.5525611
A54: ingenuo | B54: 2 | C54: 2516 | D54: 12.668407 | E54: 12.201162
A55: ingenuo | B55: 3 | C55: 2516 | D55: 18.431049 | E55: 18.22658
A56: tendencia3 | B56: 1 | C56: 2516 | D56: 6.5905132 | E56: 1.1940533 | F56: sim
A57: tendencia3 | B57: 2 | C57: 2516 | D57: 9.3520359 | E57: 3.4841463 | F57: sim
A58: tendencia3 | B58: 3 | C58: 2516 | D58: 12.532697 | E58: 5.1510564 | F58: sim
A59: tendencia5 | B59: 1 | C59: 2516 | D59: 6.8462125 | E59: 3.652036
A60: tendencia5 | B60: 2 | C60: 2516 | D60: 9.9990164 | E60: 6.6751016
A61: tendencia5 | B61: 3 | C61: 2516 | D61: 13.267662 | E61: 9.0749844
A63: Quanto da realidade caiu dentro da faixa, deixando uma origem de fora
A64: Nível da faixa (%) | B64: Origem que ficou de fora | C64: Valores testados | D64: Dentro, sem ajuste (%) | E64: Dentro, com ajuste (%)
A65: 80 | B65: 2019 | C65: 1887 | D65: 76.947536 | E65: 84.36672
A66: 80 | B66: 2020 | C66: 1887 | D66: 81.45204 | E66: 89.136195
A67: 80 | B67: 2021 | C67: 1887 | D67: 80.763116 | E67: 88.553259
A68: 80 | B68: 2022 | C68: 1887 | D68: 46.051934 | E68: 61.791203
A69: 95 | B69: 2019 | C69: 1887 | D69: 91.202968 | E69: 94.5416
A70: 95 | B70: 2020 | C70: 1887 | D70: 95.866455 | E70: 97.45628
A71: 95 | B71: 2021 | C71: 1887 | D71: 95.495495 | E71: 97.138315
A72: 95 | B72: 2022 | C72: 1887 | D72: 84.578696 | E72: 91.308956

Sheet Indicadores
A1: Indicadores: definição escrita
A2: Cada Indicador tem fórmula, fonte, periodicidade e meta escritas. Sem isso, dois analistas calculam números diferentes com o mesmo nome.
A4: Indicador | B4: Unidade | C4: Fórmula | D4: Fonte | E4: Periodicidade | F4: Meta | G4: Leitura de apoio
A5: Receita corrente por habitante | B5: R$ por habitante, a preços de 2025 | C5: (receitas correntes brutas realizadas − dedução do Fundeb − outras deduções) ÷ população, deflacionado pelo IPCA para a média de 2025 | D5: Siconfi/Tesouro Nacional, DCA Anexo I-C; população do mesmo registro (IBGE); IPCA do IBGE (SIDRA 1737) | E5: Anual | F5: Sem meta nesta amostra: o município a define na lei orçamentária | G5: Mais ou menos depende da escolha do município; não é acerto nem erro.
A6: Dependência de transferências | B6: % da receita corrente | C6: transferências correntes brutas realizadas ÷ receitas correntes brutas realizadas × 100 | D6: Siconfi/Tesouro Nacional, DCA Anexo I-C | E6: Anual | F6: Sem meta nesta amostra | G6: Mais ou menos depende da escolha do município; não é acerto nem erro.
A7: Despesa com saúde por habitante | B7: R$ por habitante, a preços de 2025 | C7: despesa empenhada na função 10 (Saúde) ÷ população, deflacionada pelo IPCA para a média de 2025 | D7: Siconfi/Tesouro Nacional, DCA Anexo I-E; população do mesmo registro (IBGE); IPCA do IBGE | E7: Anual | F7: Sem meta nesta amostra (o piso constitucional é medido sobre a receita de impostos, outro indicador) | G7: Mais ou menos depende da escolha do município; não é acerto nem erro.
A8: Despesa com educação por habitante | B8: R$ por habitante, a preços de 2025 | C8: despesa empenhada na função 12 (Educação) ÷ população, deflacionada pelo IPCA para a média de 2025 | D8: Siconfi/Tesouro Nacional, DCA Anexo I-E; população do mesmo registro (IBGE); IPCA do IBGE | E8: Anual | F8: Sem meta nesta amostra (o piso constitucional é medido sobre a receita de impostos, outro indicador) | G8: Mais ou menos depende da escolha do município; não é acerto nem erro.
A9: PIB por habitante | B9: R$ por habitante, a preços de 2025 | C9: PIB municipal a preços correntes × 1.000 ÷ população, deflacionado pelo IPCA para a média de 2025 | D9: IBGE, Produto Interno Bruto dos Municípios (SIDRA 5938); população do Siconfi (IBGE); IPCA do IBGE | E9: Anual, com defasagem de dois anos (último ano publicado: 2023) | F9: Sem meta | G9: Valor maior costuma indicar situação mais favorável, mas leia com o contexto.
A10: Ideb dos anos iniciais, rede municipal | B10: nota de 0 a 10 | C10: Ideb observado (fluxo escolar × desempenho no Saeb), 1º ao 5º ano, escolas da rede municipal | D10: INEP, Ideb 2023, divulgação por município | E10: Bienal (2015, 2017, 2019, 2021, 2023) | F10: A meta do Ideb é do INEP e vai até 2021; não entra nesta amostra | G10: Valor maior costuma indicar situação mais favorável, mas leia com o contexto.
A11: Nascidos de mães com 7 ou mais consultas de pré-natal | B11: % dos nascidos vivos com número de consultas informado | C11: nascidos vivos de mães com 7 ou mais consultas de pré-natal ÷ nascidos vivos com o número de consultas informado × 100, pelo município de residência da mãe | D11: SINASC/DataSUS, Declaração de Nascido Vivo (arquivos DNSP, ano de nascimento) | E11: Anual | F11: Sem meta nesta amostra | G11: Valor maior costuma indicar situação mais favorável, mas leia com o contexto.
A12: Receita corrente total | B12: R$ milhões, a preços de 2025 | C12: receitas correntes brutas realizadas − dedução do Fundeb − outras deduções, deflacionado pelo IPCA para a média de 2025 | D12: Siconfi/Tesouro Nacional, DCA Anexo I-C; IPCA do IBGE (SIDRA 1737) | E12: Anual | F12: Sem meta nesta amostra. É a série que o modelo de previsão usa, porque não depende da população | G12: Mais ou menos depende da escolha do município; não é acerto nem erro.
A14: Municípios parecidos: a faixa de porte
A15: Municípios parecidos são os da mesma faixa de população do Censo 2022: até 5 mil, de 5 a 10 mil, de 10 a 20 mil, de 20 a 50 mil, de 50 a 100 mil, de 100 a 500 mil e mais de 500 mil habitantes. Porte é só um critério: dois municípios do mesmo porte podem ter estruturas muito diferentes (turismo, indústria, região metropolitana). Use a comparação como ponto de partida para perguntas, e não como veredito.

Sheet Fontes e licenças
A1: Fontes, licenças e como cada uma foi verificada
A2: Consulta feita em 14/10/2026. "Verificado" quer dizer que o texto da página foi lido nesse dia; "não verificado" quer dizer que não consegui ler o texto da licença da base.
A4: Base | B4: Órgão | C4: O que foi usado | D4: Endereço | E4: Condição de uso encontrada | F4: Situação da verificação
A5: Declaração de Contas Anuais (DCA), anexos I-C e I-E | B5: Tesouro Nacional (Siconfi) | C5: Receitas correntes, deduções, transferências e despesa por função, 2015 a 2025 | D5: https://apidatalake.tesouro.gov.br/docs/siconfi/ | E5: A página de APIs do Tesouro diz que os dados são "disponibilizados para livre utilização". Não encontrei na página uma instrução de citação. | F5: Verificado em https://www.gov.br/tesouronacional/pt-br/central-de-conteudo/apis (14/10/2026). Texto de licença formal da base: não encontrado.
A6: Estimativas da população (tabela 6579) e Censo 2022 (tabela 9514) | B6: IBGE (SIDRA) | C6: População residente por município | D6: https://apisidra.ibge.gov.br/ | E6: Dado aberto de órgão federal, sujeito ao Decreto 8.777/2016: "licença aberta que permita sua livre utilização, consumo ou cruzamento, limitando-se a creditar a autoria ou a fonte". | F6: Páginas de termos de uso do IBGE bloqueiam acesso automatizado (HTTP 403); o texto próprio do IBGE não foi lido. A condição acima vem do Decreto.
A7: Produto Interno Bruto dos Municípios (tabela 5938) | B7: IBGE (SIDRA) | C7: PIB a preços correntes, 2015 a 2023 | D7: https://apisidra.ibge.gov.br/ | E7: Igual à linha anterior. | F7: Igual à linha anterior.
A8: IPCA, número-índice (tabela 1737) | B8: IBGE (SIDRA) | C8: Deflator mensal, 2015 a 2025 | D8: https://apisidra.ibge.gov.br/ | E8: Igual às linhas do IBGE. | F8: Igual às linhas do IBGE.
A9: Lista de municípios e regiões geográficas imediatas | B9: IBGE (API de Localidades) | C9: Nome, código e região | D9: https://servicodados.ibge.gov.br/api/docs | E9: Igual às linhas do IBGE. | F9: Igual às linhas do IBGE.
A10: Ideb, anos iniciais, por município (divulgação 2023) | B10: INEP | C10: Ideb observado de 2015 a 2023, rede municipal | D10: https://download.inep.gov.br/ideb/resultados/divulgacao_anos_iniciais_municipios_2023.xlsx | E10: A Política de Dados Abertos do Inep (Portaria nº 380/2020) define dados abertos como os disponibilizados "sob licença aberta que permita sua livre utilização, consumo ou cruzamento, limitando-se a creditar sua autoria ou a fonte". O CC BY 4.0 como licença padrão aparece em fonte secundária (Portaria nº 496/2021). | F10: Portaria 380/2020 lida no PDF da política do Inep (14/10/2026). A Portaria 496/2021 não foi lida em fonte primária.
A11: SINASC: Declarações de Nascido Vivo, arquivos DNSP de 2015 a 2024 | B11: Ministério da Saúde (DataSUS) | C11: Contagem de nascidos vivos por consultas de pré-natal e município de residência da mãe | D11: ftp://ftp.datasus.gov.br/dissemin/publicos/SINASC/1996_/Dados/DNRES/ | E11: A página do Ministério diz que "os dados estão disponíveis de forma pública e anonimizada". O rodapé dos sites do Ministério traz "Creative Commons Atribuição-SemDerivações 3.0" para o conteúdo do site, não declarado para os arquivos de dados. | F11: Páginas lidas em 14/10/2026. A licença do arquivo de microdados não está escrita no FTP; a condição vem do Decreto 8.777/2016 (credite a fonte).
A13: Pendente: ler o texto de licença próprio de cada órgão (IBGE e Tesouro em especial) antes de a amostra ser publicada fora da Shark, e validar a redação da atribuição com advogado. Esta aba não é parecer jurídico.

Sheet Dados
A1: Chave | B1: Código IBGE | C1: Município | D1: Ano | E1: Faixa de porte | F1: Receita corrente por habitante | G1: Dependência de transferências | H1: Despesa com saúde por habitante | I1: Despesa com educação por habitante | J1: PIB por habitante | K1: Ideb dos anos iniciais, rede municipal | L1: Nascidos de mães com 7 ou mais consultas de pré-natal | M1: Receita corrente total
A2: 3500105|2015 | B2: 3500105 | C2: Adamantina | D2: 2015 | E2: 4. De 20 a 50 mil | F2: 5447.7362 | G2: 57.266428 | H2: 1450.9263 | I2: 1796.2676 | J2: 51186.584 | K2: 6.6 | L2: 91.596639 | M2: 190.93226
A3: 3500105|2016 | B3: 3500105 | C3: Adamantina | D3: 2016 | E3: 4. De 20 a 50 mil | F3: 5767.3477 | G3: 53.009427 | H3: 1312.3488 | I3: 1777.9972 | J3: 43499.104 | K3: n.d. | L3: 92.411924 | M3: 202.3993
A4: 3500105|2017 | B4: 3500105 | C4: Adamantina | D4: 2017 | E4: 4. De 20 a 50 mil | F4: 6473.5484 | G4: 47.015896 | H4: 1323.5809 | I4: 2129.6601 | J4: 44603.647 | K4: 6.9 | L4: 94.767442 | M4: 227.47402
A5: 3500105|2018 | B5: 3500105 | C5: Adamantina | D5: 2018 | E5: 4. De 20 a 50 mil | F5: 6764.9361 | G5: 48.440512 | H5: 1496.5805 | I5: 3067.9377 | J5: 44417.139 | K5: n.d. | L5: 94.808743 | M5: 236.92836
A6: 3500105|2019 | B6: 3500105 | C6: Adamantina | D6: 2019 | E6: 4. De 20 a 50 mil | F6: 7232.244 | G6: 48.024391 | H6: 1585.1378 | I6: 3472.4349 | J6: 47564.588 | K6: 6.8 | L6: 93.129771 | M6: 253.62033
A7: 3500105|2020 | B7: 3500105 | C7: Adamantina | D7: 2020 | E7: 4. De 20 a 50 mil | F7: 7773.3067 | G7: 52.320095 | H7: 2006.4602 | I7: 3572.8249 | J7: 48061.915 | K7: n.d. | L7: 90.837696 | M7: 272.92857
A8: 3500105|2021 | B8: 3500105 | C8: Adamantina | D8: 2021 | E8: 4. De 20 a 50 mil | F8: 7627.6673 | G8: 50.823275 | H8: 2004.5513 | I8: 3299.79 | J8: 48854.255 | K8: 6.3 | L8: 85.714286 | M8: 268.13539
A9: 3500105|2022 | B9: 3500105 | C9: Adamantina | D9: 2022 | E9: 4. De 20 a 50 mil | F9: 8273.6964 | G9: 50.513929 | H9: 1795.2102 | I9: 3597.1983 | J9: 50965.584 | K9: n.d. | L9: 85.301837 | M9: 286.98971
A10: 3500105|2023 | B10: 3500105 | C10: Adamantina | D10: 2023 | E10: 4. De 20 a 50 mil | F10: 8235.1382 | G10: 49.108936 | H10: 1927.3278 | I10: 3940.8163 | J10: 53170.601 | K10: 6.5 | L10: 92.777778 | M10: 289.58452
A11: 3500105|2024 | B11: 3500105 | C11: Adamantina | D11: 2024 | E11: 4. De 20 a 50 mil | F11: 8559.1678 | G11: 51.733195 | H11: 2137.6532 | I11: 3941.2775 | J11: n.d. | K11: n.d. | L11: 92.351275 | M11: 305.06586
A12: 3500105|2025 | B12: 3500105 | C12: Adamantina | D12: 2025 | E12: 4. De 20 a 50 mil | F12: 8855.9951 | G12: 51.896637 | H12: 2299.467 | I12: 4292.6758 | J12: n.d. | K12: n.d. | L12: n.d. | M12: 315.91991
A13: 3500204|2015 | B13: 3500204 | C13: Adolfo | D13: 2015 | E13: 1. Até 5 mil | F13: 9706.9012 | G13: 90.711164 | H13: 2253.8808 | I13: 2589.5011 | J13: 34461.632 | K13: 6.2 | L13: 86.538462 | M13: 35.168103
A14: 3500204|2016 | B14: 3500204 | C14: Adolfo | D14: 2016 | E14: 1. Até 5 mil | F14: 9357.8003 | G14: 93.214135 | H14: 2108.5106 | I14: 2624.6603 | J14: 39527.905 | K14: n.d. | L14: 88.888889 | M14: 33.837806
A15: 3500204|2017 | B15: 3500204 | C15: Adolfo | D15: 2017 | E15: 1. Até 5 mil | F15: 8580.4903 | G15: 88.374258 | H15: 2088.9423 | I15: 2722.997 | J15: 42106.711 | K15: 6.5 | L15: 81.578947 | M15: 30.96699
A16: 3500204|2018 | B16: 3500204 | C16: Adolfo | D16: 2018 | E16: 1. Até 5 mil | F16: 8702.5931 | G16: 90.096224 | H16: 2373.7318 | I16: 2842.4553 | J16: 37506.467 | K16: n.d. | L16: 84.782609 | M16: 31.07696
A17: 3500204|2019 | B17: 3500204 | C17: Adolfo | D17: 2019 | E17: 1. Até 5 mil | F17: 8773.9207 | G17: 89.807212 | H17: 2196.5956 | I17: 2823.5815 | J17: 44224.781 | K17: 6.4 | L17: 92.682927 | M17: 31.252705
A18: 3500204|2020 | B18: 3500204 | C18: Adolfo | D18: 2020 | E18: 1. Até 5 mil | F18: 7909.1019 | G18: 86.692432 | H18: 2016.6897 | I18: 2009.7877 | J18: 52208.379 | K18: n.d. | L18: 72.727273 | M18: 28.108948
A19: 3500204|2021 | B19: 3500204 | C19: Adolfo | D19: 2021 | E19: 1. Até 5 mil | F19: 10718.782 | G19: 87.157429 | H19: 2789.3338 | I19: 2511.5456 | J19: 40812.944 | K19: 6.3 | L19: 90.909091 | M19: 37.998083
A20: 3500204|2022 | B20: 3500204 | C20: Adolfo | D20: 2022 | E20: 1. Até 5 mil | F20: 9287.9137 | G20: 87.349665 | H20: 2494.2852 | I20: 2630.9346 | J20: 40244.505 | K20: n.d. | L20: 90.740741 | M20: 40.411713
A21: 3500204|2023 | B21: 3500204 | C21: Adolfo | D21: 2023 | E21: 1. Até 5 mil | F21: 9107.7535 | G21: 85.519065 | H21: 2649.4123 | I21: 2782.2585 | J21: 53450.52 | K21: 6.9 | L21: 93.877551 | M21: 40.206178
A22: 3500204|2024 | B22: 3500204 | C22: Adolfo | D22: 2024 | E22: 1. Até 5 mil | F22: 9725.9844 | G22: 85.749015 | H22: 2843.9306 | I22: 2974.4117 | J22: n.d. | K22: n.d. | L22: 91.489362 | M22: 43.552958
A23: 3500204|2025 | B23: 3500204 | C23: Adolfo | D23: 2025 | E23: 1. Até 5 mil | F23: 10130.298 | G23: 86.451388 | H23: 2852.2511 | I23: 3203.2219 | J23: n.d. | K23: n.d. | L23: n.d. | M23: 45.636993
A24: 3500303|2015 | B24: 3500303 | C24: Aguaí | D24: 2015 | E24: 4. De 20 a 50 mil | F24: 3304.3577 | G24: 80.29668 | H24: 962.14871 | I24: 1213.7375 | J24: 32556.116 | K24: 5.2 | L24: 74.146341 | M24: 115.19982
A25: 3500303|2016 | B25: 3500303 | C25: Aguaí | D25: 2016 | E25: 4. De 20 a 50 mil | F25: 3272.4858 | G25: 80.196281 | H25: 846.18404 | I25: 1211.8597 | J25: 39647.921 | K25: n.d. | L25: 84.575835 | M25: 115.1555
A26: 3500303|2017 | B26: 3500303 | C26: Aguaí | D26: 2017 | E26: 4. De 20 a 50 mil | F26: 3201.5707 | G26: 81.211198 | H26: 788.51132 | I26: 1070.5382 | J26: 40524.942 | K26: 6.1 | L26: 87.096774 | M26: 113.68137
A27: 3500303|2018 | B27: 3500303 | C27: Aguaí | D27: 2018 | E27: 4. De 20 a 50 mil | F27: 3364.2933 | G27: 80.837467 | H27: 858.23496 | I27: 1118.7816 | J27: 39295.589 | K27: n.d. | L27: 84.4098 | M27: 120.9598
A28: 3500303|2019 | B28: 3500303 | C28: Aguaí | D28: 2019 | E28: 4. De 20 a 50 mil | F28: 3492.813 | G28: 83.82509 | H28: 924.8162 | I28: 1241.3612 | J28: 40373.859 | K28: 6.2 | L28: 78.281623 | M28: 126.80658
A29: 3500303|2020 | B29: 3500303 | C29: Aguaí | D29: 2020 | E29: 4. De 20 a 50 mil | F29: 3559.6572 | G29: 85.502607 | H29: 1055.9325 | I29: 1085.4014 | J29: 42332.589 | K29: n.d. | L29: 82.152231 | M29: 130.45432
A30: 3500303|2021 | B30: 3500303 | C30: Aguaí | D30: 2021 | E30: 4. De 20 a 50 mil | F30: 3720.6202 | G30: 85.959134 | H30: 1080.1863 | I30: 1161.4837 | J30: 44537.929 | K30: 5.8 | L30: 83.060109 | M30: 137.59225
A31: 3500303|2022 | B31: 3500303 | C31: Aguaí | D31: 2022 | E31: 4. De 20 a 50 mil | F31: 4881.6495 | G31: 84.114445 | H31: 1132.1015 | I31: 1584.6207 | J31: 55002.408 | K31: n.d. | L31: 82.162162 | M31: 156.56426
A32: 3500303|2023 | B32: 3500303 | C32: Aguaí | D32: 2023 | E32: 4. De 20 a 50 mil | F32: 4868.916 | G32: 82.374977 | H32: 1401.5922 | I32: 1736.6241 | J32: 59858.093 | K32: 5.9 | L32: 90.47619 | M32: 158.14239
A33: 3500303|2024 | B33: 3500303 | C33: Aguaí | D33: 2024 | E33: 4. De 20 a 50 mil | F33: 5010.2682 | G33: 82.872336 | H33: 1247.3648 | I33: 1593.8308 | J33: n.d. | K33: n.d. | L33: 90.77381 | M33: 164.7777
A34: 3500303|2025 | B34: 3500303 | C34: Aguaí | D34: 2025 | E34: 4. De 20 a 50 mil | F34: 5274.5252 | G34: 80.613896 | H34: 1564.8215 | I34: 1625.3167 | J34: n.d. | K34: n.d. | L34: n.d. | M34: 173.45804
A35: 3500402|2015 | B35: 3500402 | C35: Águas da Prata | D35: 2015 | E35: 2. De 5 a 10 mil | F35: 4727.5353 | G35: 68.355968 | H35: 1307.5291 | I35: 1161.1611 | J35: 28921.195 | K35: 5.8 | L35: 76.54321 | M35: 37.93847
A36: 3500402|2016 | B36: 3500402 | C36: Águas da Prata | D36: 2016 | E36: 2. De 5 a 10 mil | F36: 4313.8685 | G36: 77.065024 | H36: 1238.277 | I36: 1132.9224 | J36: 26391.162 | K36: n.d. | L36: 81.707317 | M36: 34.79135
A37: 3500402|2017 | B37: 3500402 | C37: Águas da Prata | D37: 2017 | E37: 2. De 5 a 10 mil | F37: 4257.2692 | G37: 70.299909 | H37: 1243.8979 | I37: 1042.5185 | J37: 28725.663 | K37: 6.5 | L37: 77.21519 | M37: 34.500909
A38: 3500402|2018 | B38: 3500402 | C38: Águas da Prata | D38: 2018 | E38: 2. De 5 a 10 mil | F38: 4077.6757 | G38: 76.531566 | H38: 1158.2208 | I38: 975.46325 | J38: 29770.693 | K38: n.d. | L38: 76.190476 | M38: 33.180047
A39: 3500402|2019 | B39: 3500402 | C39: Águas da Prata | D39: 2019 | E39: 2. De 5 a 10 mil | F39: 4654.5538 | G39: 72.276905 | H39: 1133.4645 | I39: 1064.7834 | J39: 29518.114 | K39: 6.6 | L39: 90.384615 | M39: 38.07425
A40: 3500402|2020 | B40: 3500402 | C40: Águas da Prata | D40: 2020 | E40: 2. De 5 a 10 mil | F40: 5242.747 | G40: 69.393783 | H40: 1060.5784 | I40: 834.70357 | J40: 30861.678 | K40: n.d. | L40: 84.615385 | M40: 43.100623
A41: 3500402|2021 | B41: 3500402 | C41: Águas da Prata | D41: 2021 | E41: 2. De 5 a 10 mil | F41: 5228.6543 | G41: 70.533907 | H41: 1036.2559 | I41: 917.48084 | J41: 31691.237 | K41: 6.5 | L41: 83.606557 | M41: 43.199142
A42: 3500402|2022 | B42: 3500402 | C42: Águas da Prata | D42: 2022 | E42: 2. De 5 a 10 mil | F42: 6684.4846 | G42: 73.31054 | H42: 1301.501 | I42: 1319.9398 | J42: 36939.142 | K42: n.d. | L42: 91.304348 | M42: 49.257967
A43: 3500402|2023 | B43: 3500402 | C43: Águas da Prata | D43: 2023 | E43: 2. De 5 a 10 mil | F43: 6726.194 | G43: 68.16997 | H43: 1536.4102 | I43: 1455.8812 | J43: 40233.777 | K43: 6.3 | L43: 82.45614 | M43: 49.904996
A44: 3500402|2024 | B44: 3500402 | C44: Águas da Prata | D44: 2024 | E44: 2. De 5 a 10 mil | F44: 7336.1635 | G44: 66.242395 | H44: 1818.4517 | I44: 1556.637 | J44: n.d. | K44: n.d. | L44: 83.636364 | M44: 54.801141
A45: 3500402|2025 | B45: 3500402 | C45: Águas da Prata | D45: 2025 | E45: 2. De 5 a 10 mil | F45: 7368.9981 | G45: 74.669754 | H45: 1839.6874 | I45: 1392.6142 | J45: n.d. | K45: n.d. | L45: n.d. | M45: 54.994832
A46: 3500501|2015 | B46: 3500501 | C46: Águas de Lindóia | D46: 2015 | E46: 3. De 10 a 20 mil | F46: 5980.9159 | G46: 56.844191 | H46: 1429.4897 | I46: 2279.3925 | J46: 43498.215 | K46: 6.1 | L46: 79.723502 | M46: 109.52851
A47: 3500501|2016 | B47: 3500501 | C47: Águas de Lindóia | D47: 2016 | E47: 3. De 10 a 20 mil | F47: 5981.6373 | G47: 54.597305 | H47: 1215.9462 | I47: 2083.8333 | J47: 37256.299 | K47: n.d. | L47: 75.829384 | M47: 110.13391
A48: 3500501|2017 | B48: 3500501 | C48: Águas de Lindóia | D48: 2017 | E48: 3. De 10 a 20 mil | F48: 6342.4764 | G48: 50.965533 | H48: 1201.8663 | I48: 1909.5603 | J48: 38705.595 | K48: 6.8 | L48: 72.803347 | M48: 117.3929
A49: 3500501|2018 | B49: 3500501 | C49: Águas de Lindóia | D49: 2018 | E49: 3. De 10 a 20 mil | F49: 6297.7357 | G49: 50.953547 | H49: 1593.3919 | I49: 1969.3285 | J49: 38306.071 | K49: n.d. | L49: 76.142132 | M49: 117.13159
A50: 3500501|2019 | B50: 3500501 | C50: Águas de Lindóia | D50: 2019 | E50: 3. De 10 a 20 mil | F50: 6624.0626 | G50: 52.700462 | H50: 1666.0269 | I50: 1971.8407 | J50: 39730.334 | K50: 6.5 | L50: 76.771654 | M50: 123.90309
A51: 3500501|2020 | B51: 3500501 | C51: Águas de Lindóia | D51: 2020 | E51: 3. De 10 a 20 mil | F51: 6556.2803 | G51: 56.465525 | H51: 1748.7537 | I51: 1795.7625 | J51: 35519.52 | K51: n.d. | L51: 77.868852 | M51: 123.31052
A52: 3500501|2021 | B52: 3500501 | C52: Águas de Lindóia | D52: 2021 | E52: 3. De 10 a 20 mil | F52: 6537.4542 | G52: 57.68279 | H52: 1778.3674 | I52: 1678.5142 | J52: 38799.687 | K52: 6.6 | L52: 87.946429 | M52: 123.61018
A53: 3500501|2022 | B53: 3500501 | C53: Águas de Lindóia | D53: 2022 | E53: 3. De 10 a 20 mil | F53: 7682.4648 | G53: 54.139963 | H53: 1966.9722 | I53: 2344.0391 | J53: 45368.651 | K53: n.d. | L53: 83.098592 | M53: 137.74659
A54: 3500501|2023 | B54: 3500501 | C54: Águas de Lindóia | D54: 2023 | E54: 3. De 10 a 20 mil | F54: 8159.293 | G54: 51.337029 | H54: 2144.8885 | I54: 2544.996 | J54: 48544.5 | K54: 6.7 | L54: 88.181818 | M54: 147.58121
A55: 3500501|2024 | B55: 3500501 | C55: Águas de Lindóia | D55: 2024 | E55: 3. De 10 a 20 mil | F55: 8506.9389 | G55: 51.926343 | H55: 2291.6172 | I55: 2497.1938 | J55: n.d. | K55: n.d. | L55: 85.92233 | M55: 155.2091
A56: 3500501|2025 | B56: 3500501 | C56: Águas de Lindóia | D56: 2025 | E56: 3. De 10 a 20 mil | F56: 9301.9805 | G56: 50.782567 | H56: 2216.248 | I56: 2704.4605 | J56: n.d. | K56: n.d. | L56: n.d. | M56: 169.82626
A57: 3500550|2015 | B57: 3500550 | C57: Águas de Santa Bárbara | D57: 2015 | E57: 2. De 5 a 10 mil | F57: 7974.9106 | G57: 69.799527 | H57: 1926.7255 | I57: 2259.9671 | J57: 34490.657 | K57: 6.7 | L57: 76.190476 | M57: 47.402869
A58: 3500550|2016 | B58: 3500550 | C58: Águas de Santa Bárbara | D58: 2016 | E58: 2. De 5 a 10 mil | F58: 6575.6173 | G58: 71.157199 | H58: 1832.8993 | I58: 2172.5892 | J58: 39762.629 | K58: n.d. | L58: 72.093023 | M58: 39.302464
A59: 3500550|2017 | B59: 3500550 | C59: Águas de Santa Bárbara | D59: 2017 | E59: 2. De 5 a 10 mil | F59: 7486.356 | G59: 72.189954 | H59: 1586.5437 | I59: 2102.8165 | J59: 37711.722 | K59: 6.9 | L59: 77.464789 | M59: 44.985513
A60: 3500550|2018 | B60: 3500550 | C60: Águas de Santa Bárbara | D60: 2018 | E60: 2. De 5 a 10 mil | F60: 8552.1954 | G60: 67.493015 | H60: 1861.7712 | I60: 2074.8437 | J60: 40122.997 | K60: n.d. | L60: 64.615385 | M60: 51.65526
A61: 3500550|2019 | B61: 3500550 | C61: Águas de Santa Bárbara | D61: 2019 | E61: 2. De 5 a 10 mil | F61: 8029.9035 | G61: 64.102432 | H61: 1841.2791 | I61: 2336.7876 | J61: 40243.869 | K61: 6.9 | L61: 82.352941 | M61: 48.781664
A62: 3500550|2020 | B62: 3500550 | C62: Águas de Santa Bárbara | D62: 2020 | E62: 2. De 5 a 10 mil | F62: 8165.5798 | G62: 66.058206 | H62: 1934.6717 | I62: 1959.0442 | J62: 44518.753 | K62: n.d. | L62: 76.388889 | M62: 49.883527
A63: 3500550|2021 | B63: 3500550 | C63: Águas de Santa Bárbara | D63: 2021 | E63: 2. De 5 a 10 mil | F63: 9999.7949 | G63: 59.848882 | H63: 2094.6506 | I63: 2784.2758 | J63: 44321.219 | K63: 6.2 | L63: 68.055556 | M63: 61.41874
A64: 3500550|2022 | B64: 3500550 | C64: Águas de Santa Bárbara | D64: 2022 | E64: 2. De 5 a 10 mil | F64: 8128.1854 | G64: 67.162902 | H64: 1936.2183 | I64: 2697.4054 | J64: 40701.848 | K64: n.d. | L64: 76.923077 | M64: 58.335987
A65: 3500550|2023 | B65: 3500550 | C65: Águas de Santa Bárbara | D65: 2023 | E65: 2. De 5 a 10 mil | F65: 8442.159 | G65: 63.566292 | H65: 1956.7262 | I65: 2721.9117 | J65: 56449.318 | K65: 6.3 | L65: 83.561644 | M65: 61.560223
A66: 3500550|2024 | B66: 3500550 | C66: Águas de Santa Bárbara | D66: 2024 | E66: 2. De 5 a 10 mil | F66: 9197.2218 | G66: 63.550707 | H66: 2326.4398 | I66: 2434.784 | J66: n.d. | K66: n.d. | L66: 91.666667 | M66: 68.123822
A67: 3500550|2025 | B67: 3500550 | C67: Águas de Santa Bárbara | D67: 2025 | E67: 2. De 5 a 10 mil | F67: 10048.013 | G67: 64.555474 | H67: 2324.1716 | I67: 2935.2858 | J67: n.d. | K67: n.d. | L67: n.d. | M67: 74.958176
A68: 3500600|2015 | B68: 3500600 | C68: Águas de São Pedro | D68: 2015 | E68: 1. Até 5 mil | F68: 10822.399 | G68: 58.372327 | H68: 2256.3761 | I68: 2741.4276 | J68: 67622.07 | K68: 7 | L68: 88.461538 | M68: 33.971509
A69: 3500600|2016 | B69: 3500600 | C69: Águas de São Pedro | D69: 2016 | E69: 1. Até 5 mil | F69: 11201.551 | G69: 65.107732 | H69: 2034.8185 | I69: 2804.6431 | J69: 58332.754 | K69: n.d. | L69: 86.206897 | M69: 35.90097
A70: 3500600|2017 | B70: 3500600 | C70: Águas de São Pedro | D70: 2017 | E70: 1. Até 5 mil | F70: 9887.1936 | G70: 63.904549 | H70: 2199.0069 | I70: 2712.3194 | J70: 61196.69 | K70: 7.4 | L70: 81.081081 | M70: 32.311349
A71: 3500600|2018 | B71: 3500600 | C71: Águas de São Pedro | D71: 2018 | E71: 1. Até 5 mil | F71: 10614.285 | G71: 65.072847 | H71: 2482.6797 | I71: 2561.5623 | J71: 58410.222 | K71: n.d. | L71: 100 | M71: 35.876283
A72: 3500600|2019 | B72: 3500600 | C72: Águas de São Pedro | D72: 2019 | E72: 1. Até 5 mil | F72: 10904.353 | G72: 58.362009 | H72: 2570.8547 | I72: 3386.8507 | J72: 59253.822 | K72: 7.4 | L72: n.d. | M72: 37.630923
A73: 3500600|2020 | B73: 3500600 | C73: Águas de São Pedro | D73: 2020 | E73: 1. Até 5 mil | F73: 9404.0761 | G73: 69.293547 | H73: 2652.3321 | I73: 2922.782 | J73: 52572.46 | K73: n.d. | L73: 97.142857 | M73: 33.111752
A74: 3500600|2021 | B74: 3500600 | C74: Águas de São Pedro | D74: 2021 | E74: 1. Até 5 mil | F74: 7802.8487 | G74: 91.577533 | H74: 2767.3491 | I74: 3259.6767 | J74: 51624.203 | K74: 6.9 | L74: 92.857143 | M74: 27.996621
A75: 3500600|2022 | B75: 3500600 | C75: Águas de São Pedro | D75: 2022 | E75: 1. Até 5 mil | F75: 15725.023 | G75: 68.096342 | H75: 4559.1581 | I75: 4481.887 | J75: 66252.94 | K75: n.d. | L75: 90.47619 | M75: 43.715564
A76: 3500600|2023 | B76: 3500600 | C76: Águas de São Pedro | D76: 2023 | E76: 1. Até 5 mil | F76: 17465.397 | G76: 64.308409 | H76: 4635.4735 | I76: 5274.6104 | J76: 72452.7 | K76: 7.1 | L76: 93.333333 | M76: 48.981705
A77: 3500600|2024 | B77: 3500600 | C77: Águas de São Pedro | D77: 2024 | E77: 1. Até 5 mil | F77: 19746.485 | G77: 64.688932 | H77: 5670.0852 | I77: 5559.2624 | J77: n.d. | K77: n.d. | L77: n.d. | M77: 55.862807
A78: 3500600|2025 | B78: 3500600 | C78: Águas de São Pedro | D78: 2025 | E78: 1. Até 5 mil | F78: 18265.652 | G78: 67.918965 | H78: 4978.8297 | I78: 5618.893 | J78: n.d. | K78: n.d. | L78: n.d. | M78: 53.481829
A79: 3500709|2015 | B79: 3500709 | C79: Agudos | D79: 2015 | E79: 4. De 20 a 50 mil | F79: 5687.7137 | G79: 90.802993 | H79: 1772.7031 | I79: 1395.1349 | J79: 122687.54 | K79: 6.2 | L79: 77.663934 | M79: 207.73806
A80: 3500709|2016 | B80: 3500709 | C80: Agudos | D80: 2016 | E80: 4. De 20 a 50 mil | F80: 5449.1397 | G80: 91.008105 | H80: 2070.5515 | I80: 1605.5806 | J80: 82028.411 | K80: n.d. | L80: 79.019608 | M80: 200.00522
A81: 3500709|2017 | B81: 3500709 | C81: Agudos | D81: 2017 | E81: 4. De 20 a 50 mil | F81: 5540.4794 | G81: 91.77163 | H81: 2005.7674 | I81: 1582.3571 | J81: 83583.437 | K81: 6.5 | L81: 81.109185 | M81: 204.33288
A82: 3500709|2018 | B82: 3500709 | C82: Agudos | D82: 2018 | E82: 4. De 20 a 50 mil | F82: 5813.5354 | G82: 88.715237 | H82: 2046.4443 | I82: 1643.6673 | J82: 86397.268 | K82: n.d. | L82: 74.033149 | M82: 215.23452
A83: 3500709|2019 | B83: 3500709 | C83: Agudos | D83: 2019 | E83: 4. De 20 a 50 mil | F83: 6087.9516 | G83: 85.755225 | H83: 2091.7605 | I83: 1786.3849 | J83: 80783.748 | K83: 6.5 | L83: 77.882798 | M83: 226.55703
A84: 3500709|2020 | B84: 3500709 | C84: Agudos | D84: 2020 | E84: 4. De 20 a 50 mil | F84: 5781.1155 | G84: 88.799502 | H84: 2064.7198 | I84: 1618.8349 | J84: 83750.516 | K84: n.d. | L84: 76.938776 | M84: 216.2195
A85: 3500709|2021 | B85: 3500709 | C85: Agudos | D85: 2021 | E85: 4. De 20 a 50 mil | F85: 5758.979 | G85: 89.75205 | H85: 1848.2379 | I85: 1482.1221 | J85: 87956.358 | K85: 6.1 | L85: 78.893443 | M85: 216.43395
A86: 3500709|2022 | B86: 3500709 | C86: Agudos | D86: 2022 | E86: 4. De 20 a 50 mil | F86: 5848.226 | G86: 89.188085 | H86: 1995.2934 | I86: 1663.5837 | J86: 81702.285 | K86: n.d. | L86: 78.496868 | M86: 220.36116
A87: 3500709|2023 | B87: 3500709 | C87: Agudos | D87: 2023 | E87: 4. De 20 a 50 mil | F87: 5475.7751 | G87: 86.623072 | H87: 1956.0561 | I87: 1631.3204 | J87: 97802.744 | K87: 6.3 | L87: 79.957356 | M87: 209.60993
A88: 3500709|2024 | B88: 3500709 | C88: Agudos | D88: 2024 | E88: 4. De 20 a 50 mil | F88: 5668.5213 | G88: 87.343921 | H88: 1932.5089 | I88: 1552.658 | J88: n.d. | K88: n.d. | L88: 78.118162 | M88: 220.38644
A89: 3500709|2025 | B89: 3500709 | C89: Agudos | D89: 2025 | E89: 4. De 20 a 50 mil | F89: 6060.4574 | G89: 87.205211 | H89: 1836.7519 | I89: 1740.8417 | J89: n.d. | K89: n.d. | L89: n.d. | M89: 236.28511
A90: 3500758|2015 | B90: 3500758 | C90: Alambari | D90: 2015 | E90: 2. De 5 a 10 mil | F90: 5199.6293 | G90: 84.013107 | H90: 1432.7732 | I90: 1746.1068 | J90: 25789.992 | K90: 6.2 | L90: 83.870968 | M90: 28.909939
A91: 3500758|2016 | B91: 3500758 | C91: Alambari | D91: 2016 | E91: 2. De 5 a 10 mil | F91: 5084.1606 | G91: 87.004939 | H91: 1341.6803 | I91: 1621.1846 | J91: 25340.005 | K91: n.d. | L91: 87.341772 | M91: 28.766181
A92: 3500758|2017 | B92: 3500758 | C92: Alambari | D92: 2017 | E92: 2. De 5 a 10 mil | F92: 4802.1367 | G92: 87.563392 | H92: 1313.3058 | I92: 1511.9588 | J92: 26916.396 | K92: 6.8 | L92: 83.823529 | M92: 27.631495
A93: 3500758|2018 | B93: 3500758 | C93: Alambari | D93: 2018 | E93: 2. De 5 a 10 mil | F93: 4675.0415 | G93: 88.01224 | H93: 1237.0349 | I93: 1532.4205 | J93: 24173.373 | K93: n.d. | L93: 83.823529 | M93: 27.666896
A94: 3500758|2019 | B94: 3500758 | C94: Alambari | D94: 2019 | E94: 2. De 5 a 10 mil | F94: 4853.64 | G94: 87.121368 | H94: 1227.2747 | I94: 1609.4247 | J94: 24495.642 | K94: 6.5 | L94: 75.949367 | M94: 29.243181
A95: 3500758|2020 | B95: 3500758 | C95: Alambari | D95: 2020 | E95: 2. De 5 a 10 mil | F95: 4998.8073 | G95: 87.822327 | H95: 1390.2684 | I95: 1177.6853 | J95: 26852.408 | K95: n.d. | L95: 93.548387 | M95: 30.63769
A96: 3500758|2021 | B96: 3500758 | C96: Alambari | D96: 2021 | E96: 2. De 5 a 10 mil | F96: 5215.9332 | G96: 85.501596 | H96: 1221.3408 | I96: 1464.4209 | J96: 26014.336 | K96: 5.6 | L96: 91.428571 | M96: 32.50048
A97: 3500758|2022 | B97: 3500758 | C97: Alambari | D97: 2022 | E97: 2. De 5 a 10 mil | F97: 6263.0482 | G97: 83.85448 | H97: 1488.7689 | I97: 1978.1552 | J97: 24959.951 | K97: n.d. | L97: 88.732394 | M97: 38.461379
A98: 3500758|2023 | B98: 3500758 | C98: Alambari | D98: 2023 | E98: 2. De 5 a 10 mil | F98: 6368.4679 | G98: 82.24912 | H98: 1631.5464 | I98: 2315.6104 | J98: 28167.992 | K98: 6.2 | L98: 96.969697 | M98: 39.710582
A99: 3500758|2024 | B99: 3500758 | C99: Alambari | D99: 2024 | E99: 2. De 5 a 10 mil | F99: 6414.7051 | G99: 86.928123 | H99: 1609.6117 | I99: 2051.6323 | J99: n.d. | K99: n.d. | L99: 95.522388 | M99: 40.605083
A100: 3500758|2025 | B100: 3500758 | C100: Alambari | D100: 2025 | E100: 2. De 5 a 10 mil | F100: 6907.9833 | G100: 86.396149 | H100: 1695.9826 | I100: 2359.8895 | J100: n.d. | K100: n.d. | L100: n.d. | M100: 44.024578
...

Sheet Referência
A1: Chave | B1: Faixa de porte | C1: Ano | D1: Indicador | E1: Municípios com dado | F1: Mínimo | G1: 1º quartil | H1: Mediana | I1: 3º quartil | J1: Máximo
A2: 1. Até 5 mil|2015|dependencia_transf | B2: 1. Até 5 mil | C2: 2015 | D2: dependencia_transf | E2: 150 | F2: 58.372327 | G2: 87.206672 | H2: 91.655606 | I2: 94.558115 | J2: 98.151035
A3: 1. Até 5 mil|2016|dependencia_transf | B3: 1. Até 5 mil | C3: 2016 | D3: dependencia_transf | E3: 148 | F3: 53.995872 | G3: 87.206794 | H3: 92.343886 | I3: 95.222152 | J3: 98.794207
A4: 1. Até 5 mil|2017|dependencia_transf | B4: 1. Até 5 mil | C4: 2017 | D4: dependencia_transf | E4: 150 | F4: 38.971749 | G4: 87.284162 | H4: 91.575761 | I4: 94.33804 | J4: 97.749199
A5: 1. Até 5 mil|2018|dependencia_transf | B5: 1. Até 5 mil | C5: 2018 | D5: dependencia_transf | E5: 149 | F5: 60.773138 | G5: 88.931488 | H5: 92.55173 | I5: 94.530898 | J5: 97.879496
A6: 1. Até 5 mil|2019|dependencia_transf | B6: 1. Até 5 mil | C6: 2019 | D6: dependencia_transf | E6: 145 | F6: 58.362009 | G6: 88.026683 | H6: 91.777449 | I6: 94.784222 | J6: 97.521439
A7: 1. Até 5 mil|2020|dependencia_transf | B7: 1. Até 5 mil | C7: 2020 | D7: dependencia_transf | E7: 150 | F7: 67.366517 | G7: 88.761157 | H7: 91.894841 | I7: 94.358624 | J7: 97.426161
A8: 1. Até 5 mil|2021|dependencia_transf | B8: 1. Até 5 mil | C8: 2021 | D8: dependencia_transf | E8: 150 | F8: 70.482303 | G8: 88.944618 | H8: 92.091867 | I8: 93.708255 | J8: 97.511252
A9: 1. Até 5 mil|2022|dependencia_transf | B9: 1. Até 5 mil | C9: 2022 | D9: dependencia_transf | E9: 149 | F9: 68.096342 | G9: 87.498922 | H9: 89.891428 | I9: 92.224908 | J9: 96.111841
A10: 1. Até 5 mil|2023|dependencia_transf | B10: 1. Até 5 mil | C10: 2023 | D10: dependencia_transf | E10: 150 | F10: 61.22293 | G10: 86.352196 | H10: 89.419711 | I10: 91.462783 | J10: 95.477345
A11: 1. Até 5 mil|2024|dependencia_transf | B11: 1. Até 5 mil | C11: 2024 | D11: dependencia_transf | E11: 150 | F11: 64.688932 | G11: 87.169057 | H11: 90.388004 | I11: 92.41148 | J11: 96.078943
A12: 1. Até 5 mil|2025|dependencia_transf | B12: 1. Até 5 mil | C12: 2025 | D12: dependencia_transf | E12: 149 | F12: 67.918965 | G12: 87.264449 | H12: 89.758721 | I12: 92.136353 | J12: 95.870202
A13: 2. De 5 a 10 mil|2015|dependencia_transf | B13: 2. De 5 a 10 mil | C13: 2015 | D13: dependencia_transf | E13: 122 | F13: 66.209588 | G13: 83.648439 | H13: 87.534889 | I13: 90.83679 | J13: 97.010776
... A554: 7. Mais de 500 mil|2025|saude_pc | B554: 7. Mais de 500 mil | C554: 2025 | D554: saude_pc | E554: 9 | F554: 1190.1073 | G554: 1384.8485 | H554: 1557.0186 | I554: 1848.1341 | J554: 2050.6141

Sheet Previsões
A1: Chave | B1: Código IBGE | C1: Município | D1: Ano | E1: Previsto (R$ mi) | F1: Inferior 80% | G1: Superior 80% | H1: Inferior 95% | I1: Superior 95% | J1: Método | K1: Grupo de porte do modelo
A2: 3500105|2026 | B2: 3500105 | C2: Adamantina | D2: 2026 | E2: 326.19745 | F2: 293.57251 | G2: 370.18188 | H2: 275.36842 | I2: 400.81975 | J2: tendencia3 | K2: B. De 10 a 50 mil
A3: 3500105|2027 | B3: 3500105 | C3: Adamantina | D3: 2027 | E3: 336.80934 | F3: 294.24229 | G3: 405.50463 | H3: 271.93855 | I3: 450.73512 | J3: tendencia3 | K3: B. De 10 a 50 mil
A4: 3500105|2028 | B4: 3500105 | C4: Adamantina | D4: 2028 | E4: 347.76646 | F4: 293.90381 | G4: 449.71508 | H4: 265.08773 | I4: 503.12985 | J4: tendencia3 | K4: B. De 10 a 50 mil
A5: 3500204|2026 | B5: 3500204 | C5: Adolfo | D5: 2026 | E5: 47.524798 | F5: 41.936289 | G5: 55.311859 | H5: 39.34459 | I5: 59.709568 | J5: tendencia3 | K5: A. Até 10 mil
A6: 3500204|2027 | B6: 3500204 | C6: Adolfo | D6: 2027 | E6: 49.490693 | F6: 42.353064 | G6: 63.368264 | H6: 39.193272 | I6: 70.792181 | J6: tendencia3 | K6: A. Até 10 mil
A7: 3500204|2028 | B7: 3500204 | C7: Adolfo | D7: 2028 | E7: 51.537909 | F7: 42.358068 | G7: 72.200953 | H7: 37.792488 | I7: 83.739395 | J7: tendencia3 | K7: A. Até 10 mil
A8: 3500303|2026 | B8: 3500303 | C8: Aguaí | D8: 2026 | E8: 179.48508 | F8: 161.53371 | G8: 203.68683 | H8: 151.5172 | I8: 220.54484 | J8: tendencia3 | K8: B. De 10 a 50 mil
A9: 3500303|2027 | B9: 3500303 | C9: Aguaí | D9: 2027 | E9: 185.72154 | F9: 162.24946 | G9: 223.60112 | H9: 149.95085 | I9: 248.54187 | J9: tendencia3 | K9: B. De 10 a 50 mil
A10: 3500303|2028 | B10: 3500303 | C10: Aguaí | D10: 2028 | E10: 192.1747 | F10: 162.41036 | G10: 248.51121 | H10: 146.48668 | I10: 278.02805 | J10: tendencia3 | K10: B. De 10 a 50 mil
A11: 3500402|2026 | B11: 3500402 | C11: Águas da Prata | D11: 2026 | E11: 57.051931 | F11: 50.343113 | G11: 66.400037 | H11: 47.231865 | I11: 71.67934 | J11: tendencia3 | K11: A. Até 10 mil
A12: 3500402|2027 | B12: 3500402 | C12: Águas da Prata | D12: 2027 | E12: 59.185976 | F12: 50.650078 | G12: 75.782179 | H12: 46.871279 | I12: 84.66045 | J12: tendencia3 | K12: A. Até 10 mil
A13: 3500402|2028 | B13: 3500402 | C13: Águas da Prata | D13: 2028 | E13: 61.399846 | F13: 50.463414 | G13: 86.016827 | H13: 45.024196 | I13: 99.763185 | J13: tendencia3 | K13: A. Até 10 mil
... A1927: 3557303|2028 | B1927: 3557303 | C1927: Estiva Gerbi | D1927: 2028 | E1927: 89.084287 | F1927: 75.286764 | G1927: 115.19957 | H1927: 67.905201 | I1927: 128.88237 | J1927: tendencia3 | K1927: B. De 10 a 50 mil

Sheet Municípios
A1: Código IBGE | B1: Município | C1: Faixa de porte | D1: Região geográfica imediata | E1: População (Censo 2022) | F1: Grupo de porte do modelo
A2: 3500105 | B2: Adamantina | C2: 4. De 20 a 50 mil | D2: Adamantina - Lucélia | E2: 34687 | F2: B. De 10 a 50 mil
A3: 3500204 | B3: Adolfo | C3: 1. Até 5 mil | D3: São José do Rio Preto | E3: 4351 | F3: A. Até 10 mil
A4: 3500303 | B4: Aguaí | C4: 4. De 20 a 50 mil | D4: São João da Boa Vista | E4: 32072 | F4: B. De 10 a 50 mil
A5: 3500709 | B5: Agudos | C5: 4. De 20 a 50 mil | D5: Bauru | E5: 37680 | F5: B. De 10 a 50 mil
A6: 3500758 | B6: Alambari | C6: 2. De 5 a 10 mil | D6: Itapetininga | E6: 6141 | F6: A. Até 10 mil
A7: 3500808 | B7: Alfredo Marcondes | C7: 1. Até 5 mil | D7: Presidente Prudente | E7: 4445 | F7: A. Até 10 mil
A8: 3500907 | B8: Altair | C8: 1. Até 5 mil | D8: São José do Rio Preto | E8: 3451 | F8: A. Até 10 mil
A9: 3501004 | B9: Altinópolis | C9: 3. De 10 a 20 mil | D9: Ribeirão Preto | E9: 16818 | F9: B. De 10 a 50 mil
A10: 3501103 | B10: Alto Alegre | C10: 1. Até 5 mil | D10: Birigui - Penápolis | E10: 3841 | F10: A. Até 10 mil
A11: 3501152 | B11: Alumínio | C11: 3. De 10 a 20 mil | D11: Sorocaba | E11: 17301 | F11: B. De 10 a 50 mil
A12: 3501509 | B12: Alvinlândia | C12: 1. Até 5 mil | D12: Marília | E12: 2885 | F12: A. Até 10 mil
A13: 3501608 | B13: Americana | C13: 6. De 100 a 500 mil | D13: Campinas | E13: 237240 | F13: C. Mais de 50 mil
... A646: 3533809 | B646: Óleo | C646: 1. Até 5 mil | D646: Avaré | E646: 2512 | F646: A. Até 10 mil
